<?xml version="1.0" encoding="UTF-8"?>
<jasperPrint xmlns="http://jasperreports.sourceforge.net/jasperreports/print" xmlns:xsi="http://www.w3.org/2001/XMLSchema-instance" xsi:schemaLocation="http://jasperreports.sourceforge.net/jasperreports/print http://jasperreports.sourceforge.net/xsd/jasperprint.xsd" name="null" pageWidth="595" pageHeight="842" topMargin="20" leftMargin="20" bottomMargin="20" rightMargin="20" locale="es_ES" timezone="Europe/Paris">
	<property name="net.sf.jasperreports.export.xml.start.page.index" value="0"/>
	<property name="net.sf.jasperreports.export.xml.end.page.index" value="12"/>
	<property name="net.sf.jasperreports.export.xml.page.count" value="13"/>
	<origin band="background"/>
	<origin band="title"/>
	<origin band="pageHeader"/>
	<origin band="columnHeader"/>
	<origin band="detail"/>
	<origin band="columnFooter"/>
	<origin band="pageFooter"/>
	<origin band="summary"/>
	<page>
		<image scaleImage="RetainShape" hAlign="Left" vAlign="Top">
			<reportElement uuid="0f19f0f3-5e97-46cd-b7a4-b89131653226" x="20" y="20" width="101" height="79" origin="1" srcId="1"/>
			<imageSource>
				<![CDATA[.\informes\Informe.xml_files\img_1]]>
			</imageSource>
		</image>
		<text textHeight="39.902344" lineSpacingFactor="1.3300781" leadingOffset="-7.529297">
			<reportElement uuid="4f25c38b-3021-4484-a382-d0732e3d1f15" x="147" y="50" width="328" height="49" origin="1" srcId="2"/>
			<font fontName="Segoe UI" size="30" isBold="true"/>
			<textContent><![CDATA[Informe de compras]]></textContent>
		</text>
		<text textHeight="12.578125" lineSpacingFactor="1.2578125" leadingOffset="-2.524414" valueClass="java.util.Date" pattern="dd/MM/yyyy">
			<reportElement uuid="b48e15c5-724b-44a5-a734-b740ce287ac4" x="496" y="20" width="100" height="20" origin="1" srcId="3"/>
			<textContent><![CDATA[08/05/2021]]></textContent>
		</text>
		<line>
			<reportElement uuid="27275c97-40e2-4939-8900-7574da372a65" x="20" y="172" width="555" height="1" origin="3" srcId="4"/>
		</line>
		<text textHeight="12.578125" lineSpacingFactor="1.2578125" leadingOffset="-2.524414">
			<reportElement uuid="e83b38b2-0c41-4e74-ad13-0a4c8a94c51b" x="21" y="153" width="100" height="20" origin="3" srcId="5"/>
			<font isBold="true"/>
			<textContent><![CDATA[Proveedor]]></textContent>
		</text>
		<text textHeight="12.578125" lineSpacingFactor="1.2578125" leadingOffset="-2.524414">
			<reportElement uuid="530ce9ef-a10f-4700-b00a-4ead60aebb85" x="252" y="152" width="100" height="20" origin="3" srcId="6"/>
			<font isBold="true"/>
			<textContent><![CDATA[Código postal]]></textContent>
		</text>
		<text textHeight="12.578125" lineSpacingFactor="1.2578125" leadingOffset="-2.524414">
			<reportElement uuid="132e4a73-1ca8-4139-9e8c-c0142ad86571" x="137" y="152" width="100" height="20" origin="3" srcId="7"/>
			<font isBold="true"/>
			<textContent><![CDATA[Empleado]]></textContent>
		</text>
		<text textHeight="12.578125" lineSpacingFactor="1.2578125" leadingOffset="-2.524414">
			<reportElement uuid="1ce41270-2a0f-4f83-adbe-fd7fbfc19e7e" x="375" y="152" width="100" height="20" origin="3" srcId="8"/>
			<font isBold="true"/>
			<textContent><![CDATA[Producto]]></textContent>
		</text>
		<text textHeight="12.578125" lineSpacingFactor="1.2578125" leadingOffset="-2.524414">
			<reportElement uuid="bdc6ba74-6f4c-4ecf-98ba-ab21b873471a" x="521" y="152" width="100" height="20" origin="3" srcId="9"/>
			<font isBold="true"/>
			<textContent><![CDATA[TOTAL]]></textContent>
		</text>
		<text textHeight="12.578125" lineSpacingFactor="1.2578125" leadingOffset="-2.524414">
			<reportElement uuid="f113d5ad-3f73-400a-938d-ae09cc30d3c5" x="21" y="244" width="100" height="20" origin="4" srcId="10"/>
			<textContent><![CDATA[C├ñsar Angst]]></textContent>
		</text>
		<text textHeight="12.578125" lineSpacingFactor="1.2578125" leadingOffset="-2.524414" valueClass="java.lang.Integer">
			<reportElement uuid="a1803140-cd56-49d0-915e-b4cdeee35f68" x="252" y="244" width="100" height="20" origin="4" srcId="11"/>
			<textContent><![CDATA[50]]></textContent>
		</text>
		<text textHeight="12.578125" lineSpacingFactor="1.2578125" leadingOffset="-2.524414" valueClass="java.lang.Integer">
			<reportElement uuid="9f9fefa2-eee1-4f3e-9956-c66d37e34e00" x="137" y="244" width="100" height="20" origin="4" srcId="12"/>
			<textContent><![CDATA[7]]></textContent>
		</text>
		<text textHeight="12.578125" lineSpacingFactor="1.2578125" leadingOffset="-2.524414" valueClass="java.lang.Integer">
			<reportElement uuid="e96a05ce-cdb9-4ee9-8e21-a371d7a53279" x="375" y="244" width="100" height="20" origin="4" srcId="13"/>
			<textContent><![CDATA[22]]></textContent>
		</text>
		<text textHeight="12.578125" lineSpacingFactor="1.2578125" leadingOffset="-2.524414" valueClass="java.lang.Float">
			<reportElement uuid="09dae523-39b7-4d38-93f8-c1f4e214fea8" x="521" y="244" width="100" height="20" origin="4" srcId="14"/>
			<textContent><![CDATA[197843.0]]></textContent>
		</text>
		<text textHeight="12.578125" lineSpacingFactor="1.2578125" leadingOffset="-2.524414">
			<reportElement uuid="f113d5ad-3f73-400a-938d-ae09cc30d3c5" x="21" y="369" width="100" height="20" origin="4" srcId="10"/>
			<textContent><![CDATA[Veit berl├ñnder]]></textContent>
		</text>
		<text textHeight="12.578125" lineSpacingFactor="1.2578125" leadingOffset="-2.524414" valueClass="java.lang.Integer">
			<reportElement uuid="a1803140-cd56-49d0-915e-b4cdeee35f68" x="252" y="369" width="100" height="20" origin="4" srcId="11"/>
			<textContent><![CDATA[48]]></textContent>
		</text>
		<text textHeight="12.578125" lineSpacingFactor="1.2578125" leadingOffset="-2.524414" valueClass="java.lang.Integer">
			<reportElement uuid="9f9fefa2-eee1-4f3e-9956-c66d37e34e00" x="137" y="369" width="100" height="20" origin="4" srcId="12"/>
			<textContent><![CDATA[28]]></textContent>
		</text>
		<text textHeight="12.578125" lineSpacingFactor="1.2578125" leadingOffset="-2.524414" valueClass="java.lang.Integer">
			<reportElement uuid="e96a05ce-cdb9-4ee9-8e21-a371d7a53279" x="375" y="369" width="100" height="20" origin="4" srcId="13"/>
			<textContent><![CDATA[1]]></textContent>
		</text>
		<text textHeight="12.578125" lineSpacingFactor="1.2578125" leadingOffset="-2.524414" valueClass="java.lang.Float">
			<reportElement uuid="09dae523-39b7-4d38-93f8-c1f4e214fea8" x="521" y="369" width="100" height="20" origin="4" srcId="14"/>
			<textContent><![CDATA[7526250.0]]></textContent>
		</text>
		<text textHeight="12.578125" lineSpacingFactor="1.2578125" leadingOffset="-2.524414">
			<reportElement uuid="f113d5ad-3f73-400a-938d-ae09cc30d3c5" x="21" y="494" width="100" height="20" origin="4" srcId="10"/>
			<textContent><![CDATA[Adlin  Feigenbaum]]></textContent>
		</text>
		<text textHeight="12.578125" lineSpacingFactor="1.2578125" leadingOffset="-2.524414" valueClass="java.lang.Integer">
			<reportElement uuid="a1803140-cd56-49d0-915e-b4cdeee35f68" x="252" y="494" width="100" height="20" origin="4" srcId="11"/>
			<textContent><![CDATA[56]]></textContent>
		</text>
		<text textHeight="12.578125" lineSpacingFactor="1.2578125" leadingOffset="-2.524414" valueClass="java.lang.Integer">
			<reportElement uuid="9f9fefa2-eee1-4f3e-9956-c66d37e34e00" x="137" y="494" width="100" height="20" origin="4" srcId="12"/>
			<textContent><![CDATA[27]]></textContent>
		</text>
		<text textHeight="12.578125" lineSpacingFactor="1.2578125" leadingOffset="-2.524414" valueClass="java.lang.Integer">
			<reportElement uuid="e96a05ce-cdb9-4ee9-8e21-a371d7a53279" x="375" y="494" width="100" height="20" origin="4" srcId="13"/>
			<textContent><![CDATA[27]]></textContent>
		</text>
		<text textHeight="12.578125" lineSpacingFactor="1.2578125" leadingOffset="-2.524414" valueClass="java.lang.Float">
			<reportElement uuid="09dae523-39b7-4d38-93f8-c1f4e214fea8" x="521" y="494" width="100" height="20" origin="4" srcId="14"/>
			<textContent><![CDATA[2604150.0]]></textContent>
		</text>
		<text textHeight="12.578125" lineSpacingFactor="1.2578125" leadingOffset="-2.524414">
			<reportElement uuid="f113d5ad-3f73-400a-938d-ae09cc30d3c5" x="21" y="619" width="100" height="20" origin="4" srcId="10"/>
			<textContent><![CDATA[Baldur  Jost]]></textContent>
		</text>
		<text textHeight="12.578125" lineSpacingFactor="1.2578125" leadingOffset="-2.524414" valueClass="java.lang.Integer">
			<reportElement uuid="a1803140-cd56-49d0-915e-b4cdeee35f68" x="252" y="619" width="100" height="20" origin="4" srcId="11"/>
			<textContent><![CDATA[484]]></textContent>
		</text>
		<text textHeight="12.578125" lineSpacingFactor="1.2578125" leadingOffset="-2.524414" valueClass="java.lang.Integer">
			<reportElement uuid="9f9fefa2-eee1-4f3e-9956-c66d37e34e00" x="137" y="619" width="100" height="20" origin="4" srcId="12"/>
			<textContent><![CDATA[45]]></textContent>
		</text>
		<text textHeight="12.578125" lineSpacingFactor="1.2578125" leadingOffset="-2.524414" valueClass="java.lang.Integer">
			<reportElement uuid="e96a05ce-cdb9-4ee9-8e21-a371d7a53279" x="375" y="619" width="100" height="20" origin="4" srcId="13"/>
			<textContent><![CDATA[22]]></textContent>
		</text>
		<text textHeight="12.578125" lineSpacingFactor="1.2578125" leadingOffset="-2.524414" valueClass="java.lang.Float">
			<reportElement uuid="09dae523-39b7-4d38-93f8-c1f4e214fea8" x="521" y="619" width="100" height="20" origin="4" srcId="14"/>
			<textContent><![CDATA[5696450.0]]></textContent>
		</text>
	</page>
	<page>
		<line>
			<reportElement uuid="27275c97-40e2-4939-8900-7574da372a65" x="20" y="93" width="555" height="1" origin="3" srcId="4"/>
		</line>
		<text textHeight="12.578125" lineSpacingFactor="1.2578125" leadingOffset="-2.524414">
			<reportElement uuid="e83b38b2-0c41-4e74-ad13-0a4c8a94c51b" x="21" y="74" width="100" height="20" origin="3" srcId="5"/>
			<font isBold="true"/>
			<textContent><![CDATA[Proveedor]]></textContent>
		</text>
		<text textHeight="12.578125" lineSpacingFactor="1.2578125" leadingOffset="-2.524414">
			<reportElement uuid="530ce9ef-a10f-4700-b00a-4ead60aebb85" x="252" y="73" width="100" height="20" origin="3" srcId="6"/>
			<font isBold="true"/>
			<textContent><![CDATA[Código postal]]></textContent>
		</text>
		<text textHeight="12.578125" lineSpacingFactor="1.2578125" leadingOffset="-2.524414">
			<reportElement uuid="132e4a73-1ca8-4139-9e8c-c0142ad86571" x="137" y="73" width="100" height="20" origin="3" srcId="7"/>
			<font isBold="true"/>
			<textContent><![CDATA[Empleado]]></textContent>
		</text>
		<text textHeight="12.578125" lineSpacingFactor="1.2578125" leadingOffset="-2.524414">
			<reportElement uuid="1ce41270-2a0f-4f83-adbe-fd7fbfc19e7e" x="375" y="73" width="100" height="20" origin="3" srcId="8"/>
			<font isBold="true"/>
			<textContent><![CDATA[Producto]]></textContent>
		</text>
		<text textHeight="12.578125" lineSpacingFactor="1.2578125" leadingOffset="-2.524414">
			<reportElement uuid="bdc6ba74-6f4c-4ecf-98ba-ab21b873471a" x="521" y="73" width="100" height="20" origin="3" srcId="9"/>
			<font isBold="true"/>
			<textContent><![CDATA[TOTAL]]></textContent>
		</text>
		<text textHeight="12.578125" lineSpacingFactor="1.2578125" leadingOffset="-2.524414">
			<reportElement uuid="f113d5ad-3f73-400a-938d-ae09cc30d3c5" x="21" y="165" width="100" height="20" origin="4" srcId="10"/>
			<textContent><![CDATA[Svenson Baumbach]]></textContent>
		</text>
		<text textHeight="12.578125" lineSpacingFactor="1.2578125" leadingOffset="-2.524414" valueClass="java.lang.Integer">
			<reportElement uuid="a1803140-cd56-49d0-915e-b4cdeee35f68" x="252" y="165" width="100" height="20" origin="4" srcId="11"/>
			<textContent><![CDATA[76]]></textContent>
		</text>
		<text textHeight="12.578125" lineSpacingFactor="1.2578125" leadingOffset="-2.524414" valueClass="java.lang.Integer">
			<reportElement uuid="9f9fefa2-eee1-4f3e-9956-c66d37e34e00" x="137" y="165" width="100" height="20" origin="4" srcId="12"/>
			<textContent><![CDATA[1]]></textContent>
		</text>
		<text textHeight="12.578125" lineSpacingFactor="1.2578125" leadingOffset="-2.524414" valueClass="java.lang.Integer">
			<reportElement uuid="e96a05ce-cdb9-4ee9-8e21-a371d7a53279" x="375" y="165" width="100" height="20" origin="4" srcId="13"/>
			<textContent><![CDATA[39]]></textContent>
		</text>
		<text textHeight="12.578125" lineSpacingFactor="1.2578125" leadingOffset="-2.524414" valueClass="java.lang.Float">
			<reportElement uuid="09dae523-39b7-4d38-93f8-c1f4e214fea8" x="521" y="165" width="100" height="20" origin="4" srcId="14"/>
			<textContent><![CDATA[7420570.0]]></textContent>
		</text>
		<text textHeight="12.578125" lineSpacingFactor="1.2578125" leadingOffset="-2.524414">
			<reportElement uuid="f113d5ad-3f73-400a-938d-ae09cc30d3c5" x="21" y="290" width="100" height="20" origin="4" srcId="10"/>
			<textContent><![CDATA[Gotthard G├╝nther]]></textContent>
		</text>
		<text textHeight="12.578125" lineSpacingFactor="1.2578125" leadingOffset="-2.524414" valueClass="java.lang.Integer">
			<reportElement uuid="a1803140-cd56-49d0-915e-b4cdeee35f68" x="252" y="290" width="100" height="20" origin="4" srcId="11"/>
			<textContent><![CDATA[50]]></textContent>
		</text>
		<text textHeight="12.578125" lineSpacingFactor="1.2578125" leadingOffset="-2.524414" valueClass="java.lang.Integer">
			<reportElement uuid="9f9fefa2-eee1-4f3e-9956-c66d37e34e00" x="137" y="290" width="100" height="20" origin="4" srcId="12"/>
			<textContent><![CDATA[28]]></textContent>
		</text>
		<text textHeight="12.578125" lineSpacingFactor="1.2578125" leadingOffset="-2.524414" valueClass="java.lang.Integer">
			<reportElement uuid="e96a05ce-cdb9-4ee9-8e21-a371d7a53279" x="375" y="290" width="100" height="20" origin="4" srcId="13"/>
			<textContent><![CDATA[30]]></textContent>
		</text>
		<text textHeight="12.578125" lineSpacingFactor="1.2578125" leadingOffset="-2.524414" valueClass="java.lang.Float">
			<reportElement uuid="09dae523-39b7-4d38-93f8-c1f4e214fea8" x="521" y="290" width="100" height="20" origin="4" srcId="14"/>
			<textContent><![CDATA[4797030.0]]></textContent>
		</text>
		<text textHeight="12.578125" lineSpacingFactor="1.2578125" leadingOffset="-2.524414">
			<reportElement uuid="f113d5ad-3f73-400a-938d-ae09cc30d3c5" x="21" y="415" width="100" height="20" origin="4" srcId="10"/>
			<textContent><![CDATA[Svenna cheidemann]]></textContent>
		</text>
		<text textHeight="12.578125" lineSpacingFactor="1.2578125" leadingOffset="-2.524414" valueClass="java.lang.Integer">
			<reportElement uuid="a1803140-cd56-49d0-915e-b4cdeee35f68" x="252" y="415" width="100" height="20" origin="4" srcId="11"/>
			<textContent><![CDATA[705]]></textContent>
		</text>
		<text textHeight="12.578125" lineSpacingFactor="1.2578125" leadingOffset="-2.524414" valueClass="java.lang.Integer">
			<reportElement uuid="9f9fefa2-eee1-4f3e-9956-c66d37e34e00" x="137" y="415" width="100" height="20" origin="4" srcId="12"/>
			<textContent><![CDATA[21]]></textContent>
		</text>
		<text textHeight="12.578125" lineSpacingFactor="1.2578125" leadingOffset="-2.524414" valueClass="java.lang.Integer">
			<reportElement uuid="e96a05ce-cdb9-4ee9-8e21-a371d7a53279" x="375" y="415" width="100" height="20" origin="4" srcId="13"/>
			<textContent><![CDATA[46]]></textContent>
		</text>
		<text textHeight="12.578125" lineSpacingFactor="1.2578125" leadingOffset="-2.524414" valueClass="java.lang.Float">
			<reportElement uuid="09dae523-39b7-4d38-93f8-c1f4e214fea8" x="521" y="415" width="100" height="20" origin="4" srcId="14"/>
			<textContent><![CDATA[4618050.0]]></textContent>
		</text>
		<text textHeight="12.578125" lineSpacingFactor="1.2578125" leadingOffset="-2.524414">
			<reportElement uuid="f113d5ad-3f73-400a-938d-ae09cc30d3c5" x="21" y="540" width="100" height="20" origin="4" srcId="10"/>
			<textContent><![CDATA[Landulf Kauer]]></textContent>
		</text>
		<text textHeight="12.578125" lineSpacingFactor="1.2578125" leadingOffset="-2.524414" valueClass="java.lang.Integer">
			<reportElement uuid="a1803140-cd56-49d0-915e-b4cdeee35f68" x="252" y="540" width="100" height="20" origin="4" srcId="11"/>
			<textContent><![CDATA[328]]></textContent>
		</text>
		<text textHeight="12.578125" lineSpacingFactor="1.2578125" leadingOffset="-2.524414" valueClass="java.lang.Integer">
			<reportElement uuid="9f9fefa2-eee1-4f3e-9956-c66d37e34e00" x="137" y="540" width="100" height="20" origin="4" srcId="12"/>
			<textContent><![CDATA[23]]></textContent>
		</text>
		<text textHeight="12.578125" lineSpacingFactor="1.2578125" leadingOffset="-2.524414" valueClass="java.lang.Integer">
			<reportElement uuid="e96a05ce-cdb9-4ee9-8e21-a371d7a53279" x="375" y="540" width="100" height="20" origin="4" srcId="13"/>
			<textContent><![CDATA[38]]></textContent>
		</text>
		<text textHeight="12.578125" lineSpacingFactor="1.2578125" leadingOffset="-2.524414" valueClass="java.lang.Float">
			<reportElement uuid="09dae523-39b7-4d38-93f8-c1f4e214fea8" x="521" y="540" width="100" height="20" origin="4" srcId="14"/>
			<textContent><![CDATA[2888270.0]]></textContent>
		</text>
	</page>
	<page>
		<line>
			<reportElement uuid="27275c97-40e2-4939-8900-7574da372a65" x="20" y="93" width="555" height="1" origin="3" srcId="4"/>
		</line>
		<text textHeight="12.578125" lineSpacingFactor="1.2578125" leadingOffset="-2.524414">
			<reportElement uuid="e83b38b2-0c41-4e74-ad13-0a4c8a94c51b" x="21" y="74" width="100" height="20" origin="3" srcId="5"/>
			<font isBold="true"/>
			<textContent><![CDATA[Proveedor]]></textContent>
		</text>
		<text textHeight="12.578125" lineSpacingFactor="1.2578125" leadingOffset="-2.524414">
			<reportElement uuid="530ce9ef-a10f-4700-b00a-4ead60aebb85" x="252" y="73" width="100" height="20" origin="3" srcId="6"/>
			<font isBold="true"/>
			<textContent><![CDATA[Código postal]]></textContent>
		</text>
		<text textHeight="12.578125" lineSpacingFactor="1.2578125" leadingOffset="-2.524414">
			<reportElement uuid="132e4a73-1ca8-4139-9e8c-c0142ad86571" x="137" y="73" width="100" height="20" origin="3" srcId="7"/>
			<font isBold="true"/>
			<textContent><![CDATA[Empleado]]></textContent>
		</text>
		<text textHeight="12.578125" lineSpacingFactor="1.2578125" leadingOffset="-2.524414">
			<reportElement uuid="1ce41270-2a0f-4f83-adbe-fd7fbfc19e7e" x="375" y="73" width="100" height="20" origin="3" srcId="8"/>
			<font isBold="true"/>
			<textContent><![CDATA[Producto]]></textContent>
		</text>
		<text textHeight="12.578125" lineSpacingFactor="1.2578125" leadingOffset="-2.524414">
			<reportElement uuid="bdc6ba74-6f4c-4ecf-98ba-ab21b873471a" x="521" y="73" width="100" height="20" origin="3" srcId="9"/>
			<font isBold="true"/>
			<textContent><![CDATA[TOTAL]]></textContent>
		</text>
		<text textHeight="12.578125" lineSpacingFactor="1.2578125" leadingOffset="-2.524414">
			<reportElement uuid="f113d5ad-3f73-400a-938d-ae09cc30d3c5" x="21" y="165" width="100" height="20" origin="4" srcId="10"/>
			<textContent><![CDATA[Claudelle Berens]]></textContent>
		</text>
		<text textHeight="12.578125" lineSpacingFactor="1.2578125" leadingOffset="-2.524414" valueClass="java.lang.Integer">
			<reportElement uuid="a1803140-cd56-49d0-915e-b4cdeee35f68" x="252" y="165" width="100" height="20" origin="4" srcId="11"/>
			<textContent><![CDATA[208]]></textContent>
		</text>
		<text textHeight="12.578125" lineSpacingFactor="1.2578125" leadingOffset="-2.524414" valueClass="java.lang.Integer">
			<reportElement uuid="9f9fefa2-eee1-4f3e-9956-c66d37e34e00" x="137" y="165" width="100" height="20" origin="4" srcId="12"/>
			<textContent><![CDATA[42]]></textContent>
		</text>
		<text textHeight="12.578125" lineSpacingFactor="1.2578125" leadingOffset="-2.524414" valueClass="java.lang.Integer">
			<reportElement uuid="e96a05ce-cdb9-4ee9-8e21-a371d7a53279" x="375" y="165" width="100" height="20" origin="4" srcId="13"/>
			<textContent><![CDATA[17]]></textContent>
		</text>
		<text textHeight="12.578125" lineSpacingFactor="1.2578125" leadingOffset="-2.524414" valueClass="java.lang.Float">
			<reportElement uuid="09dae523-39b7-4d38-93f8-c1f4e214fea8" x="521" y="165" width="100" height="20" origin="4" srcId="14"/>
			<textContent><![CDATA[1603150.0]]></textContent>
		</text>
		<text textHeight="12.578125" lineSpacingFactor="1.2578125" leadingOffset="-2.524414">
			<reportElement uuid="f113d5ad-3f73-400a-938d-ae09cc30d3c5" x="21" y="290" width="100" height="20" origin="4" srcId="10"/>
			<textContent><![CDATA[Justus ascher]]></textContent>
		</text>
		<text textHeight="12.578125" lineSpacingFactor="1.2578125" leadingOffset="-2.524414" valueClass="java.lang.Integer">
			<reportElement uuid="a1803140-cd56-49d0-915e-b4cdeee35f68" x="252" y="290" width="100" height="20" origin="4" srcId="11"/>
			<textContent><![CDATA[703]]></textContent>
		</text>
		<text textHeight="12.578125" lineSpacingFactor="1.2578125" leadingOffset="-2.524414" valueClass="java.lang.Integer">
			<reportElement uuid="9f9fefa2-eee1-4f3e-9956-c66d37e34e00" x="137" y="290" width="100" height="20" origin="4" srcId="12"/>
			<textContent><![CDATA[11]]></textContent>
		</text>
		<text textHeight="12.578125" lineSpacingFactor="1.2578125" leadingOffset="-2.524414" valueClass="java.lang.Integer">
			<reportElement uuid="e96a05ce-cdb9-4ee9-8e21-a371d7a53279" x="375" y="290" width="100" height="20" origin="4" srcId="13"/>
			<textContent><![CDATA[46]]></textContent>
		</text>
		<text textHeight="12.578125" lineSpacingFactor="1.2578125" leadingOffset="-2.524414" valueClass="java.lang.Float">
			<reportElement uuid="09dae523-39b7-4d38-93f8-c1f4e214fea8" x="521" y="290" width="100" height="20" origin="4" srcId="14"/>
			<textContent><![CDATA[4304060.0]]></textContent>
		</text>
		<text textHeight="12.578125" lineSpacingFactor="1.2578125" leadingOffset="-2.524414">
			<reportElement uuid="f113d5ad-3f73-400a-938d-ae09cc30d3c5" x="21" y="415" width="100" height="20" origin="4" srcId="10"/>
			<textContent><![CDATA[Sonja Simmel]]></textContent>
		</text>
		<text textHeight="12.578125" lineSpacingFactor="1.2578125" leadingOffset="-2.524414" valueClass="java.lang.Integer">
			<reportElement uuid="a1803140-cd56-49d0-915e-b4cdeee35f68" x="252" y="415" width="100" height="20" origin="4" srcId="11"/>
			<textContent><![CDATA[882]]></textContent>
		</text>
		<text textHeight="12.578125" lineSpacingFactor="1.2578125" leadingOffset="-2.524414" valueClass="java.lang.Integer">
			<reportElement uuid="9f9fefa2-eee1-4f3e-9956-c66d37e34e00" x="137" y="415" width="100" height="20" origin="4" srcId="12"/>
			<textContent><![CDATA[4]]></textContent>
		</text>
		<text textHeight="12.578125" lineSpacingFactor="1.2578125" leadingOffset="-2.524414" valueClass="java.lang.Integer">
			<reportElement uuid="e96a05ce-cdb9-4ee9-8e21-a371d7a53279" x="375" y="415" width="100" height="20" origin="4" srcId="13"/>
			<textContent><![CDATA[48]]></textContent>
		</text>
		<text textHeight="12.578125" lineSpacingFactor="1.2578125" leadingOffset="-2.524414" valueClass="java.lang.Float">
			<reportElement uuid="09dae523-39b7-4d38-93f8-c1f4e214fea8" x="521" y="415" width="100" height="20" origin="4" srcId="14"/>
			<textContent><![CDATA[7293840.0]]></textContent>
		</text>
		<text textHeight="12.578125" lineSpacingFactor="1.2578125" leadingOffset="-2.524414">
			<reportElement uuid="f113d5ad-3f73-400a-938d-ae09cc30d3c5" x="21" y="540" width="100" height="20" origin="4" srcId="10"/>
			<textContent><![CDATA[Aurita M├Âbius]]></textContent>
		</text>
		<text textHeight="12.578125" lineSpacingFactor="1.2578125" leadingOffset="-2.524414" valueClass="java.lang.Integer">
			<reportElement uuid="a1803140-cd56-49d0-915e-b4cdeee35f68" x="252" y="540" width="100" height="20" origin="4" srcId="11"/>
			<textContent><![CDATA[710]]></textContent>
		</text>
		<text textHeight="12.578125" lineSpacingFactor="1.2578125" leadingOffset="-2.524414" valueClass="java.lang.Integer">
			<reportElement uuid="9f9fefa2-eee1-4f3e-9956-c66d37e34e00" x="137" y="540" width="100" height="20" origin="4" srcId="12"/>
			<textContent><![CDATA[37]]></textContent>
		</text>
		<text textHeight="12.578125" lineSpacingFactor="1.2578125" leadingOffset="-2.524414" valueClass="java.lang.Integer">
			<reportElement uuid="e96a05ce-cdb9-4ee9-8e21-a371d7a53279" x="375" y="540" width="100" height="20" origin="4" srcId="13"/>
			<textContent><![CDATA[16]]></textContent>
		</text>
		<text textHeight="12.578125" lineSpacingFactor="1.2578125" leadingOffset="-2.524414" valueClass="java.lang.Float">
			<reportElement uuid="09dae523-39b7-4d38-93f8-c1f4e214fea8" x="521" y="540" width="100" height="20" origin="4" srcId="14"/>
			<textContent><![CDATA[6148780.0]]></textContent>
		</text>
	</page>
	<page>
		<line>
			<reportElement uuid="27275c97-40e2-4939-8900-7574da372a65" x="20" y="93" width="555" height="1" origin="3" srcId="4"/>
		</line>
		<text textHeight="12.578125" lineSpacingFactor="1.2578125" leadingOffset="-2.524414">
			<reportElement uuid="e83b38b2-0c41-4e74-ad13-0a4c8a94c51b" x="21" y="74" width="100" height="20" origin="3" srcId="5"/>
			<font isBold="true"/>
			<textContent><![CDATA[Proveedor]]></textContent>
		</text>
		<text textHeight="12.578125" lineSpacingFactor="1.2578125" leadingOffset="-2.524414">
			<reportElement uuid="530ce9ef-a10f-4700-b00a-4ead60aebb85" x="252" y="73" width="100" height="20" origin="3" srcId="6"/>
			<font isBold="true"/>
			<textContent><![CDATA[Código postal]]></textContent>
		</text>
		<text textHeight="12.578125" lineSpacingFactor="1.2578125" leadingOffset="-2.524414">
			<reportElement uuid="132e4a73-1ca8-4139-9e8c-c0142ad86571" x="137" y="73" width="100" height="20" origin="3" srcId="7"/>
			<font isBold="true"/>
			<textContent><![CDATA[Empleado]]></textContent>
		</text>
		<text textHeight="12.578125" lineSpacingFactor="1.2578125" leadingOffset="-2.524414">
			<reportElement uuid="1ce41270-2a0f-4f83-adbe-fd7fbfc19e7e" x="375" y="73" width="100" height="20" origin="3" srcId="8"/>
			<font isBold="true"/>
			<textContent><![CDATA[Producto]]></textContent>
		</text>
		<text textHeight="12.578125" lineSpacingFactor="1.2578125" leadingOffset="-2.524414">
			<reportElement uuid="bdc6ba74-6f4c-4ecf-98ba-ab21b873471a" x="521" y="73" width="100" height="20" origin="3" srcId="9"/>
			<font isBold="true"/>
			<textContent><![CDATA[TOTAL]]></textContent>
		</text>
		<text textHeight="12.578125" lineSpacingFactor="1.2578125" leadingOffset="-2.524414">
			<reportElement uuid="f113d5ad-3f73-400a-938d-ae09cc30d3c5" x="21" y="165" width="100" height="20" origin="4" srcId="10"/>
			<textContent><![CDATA[Crystle Wirt]]></textContent>
		</text>
		<text textHeight="12.578125" lineSpacingFactor="1.2578125" leadingOffset="-2.524414" valueClass="java.lang.Integer">
			<reportElement uuid="a1803140-cd56-49d0-915e-b4cdeee35f68" x="252" y="165" width="100" height="20" origin="4" srcId="11"/>
			<textContent><![CDATA[702]]></textContent>
		</text>
		<text textHeight="12.578125" lineSpacingFactor="1.2578125" leadingOffset="-2.524414" valueClass="java.lang.Integer">
			<reportElement uuid="9f9fefa2-eee1-4f3e-9956-c66d37e34e00" x="137" y="165" width="100" height="20" origin="4" srcId="12"/>
			<textContent><![CDATA[8]]></textContent>
		</text>
		<text textHeight="12.578125" lineSpacingFactor="1.2578125" leadingOffset="-2.524414" valueClass="java.lang.Integer">
			<reportElement uuid="e96a05ce-cdb9-4ee9-8e21-a371d7a53279" x="375" y="165" width="100" height="20" origin="4" srcId="13"/>
			<textContent><![CDATA[3]]></textContent>
		</text>
		<text textHeight="12.578125" lineSpacingFactor="1.2578125" leadingOffset="-2.524414" valueClass="java.lang.Float">
			<reportElement uuid="09dae523-39b7-4d38-93f8-c1f4e214fea8" x="521" y="165" width="100" height="20" origin="4" srcId="14"/>
			<textContent><![CDATA[7588170.0]]></textContent>
		</text>
		<text textHeight="12.578125" lineSpacingFactor="1.2578125" leadingOffset="-2.524414">
			<reportElement uuid="f113d5ad-3f73-400a-938d-ae09cc30d3c5" x="21" y="290" width="100" height="20" origin="4" srcId="10"/>
			<textContent><![CDATA[Wiglaf Gebbels]]></textContent>
		</text>
		<text textHeight="12.578125" lineSpacingFactor="1.2578125" leadingOffset="-2.524414" valueClass="java.lang.Integer">
			<reportElement uuid="a1803140-cd56-49d0-915e-b4cdeee35f68" x="252" y="290" width="100" height="20" origin="4" srcId="11"/>
			<textContent><![CDATA[170]]></textContent>
		</text>
		<text textHeight="12.578125" lineSpacingFactor="1.2578125" leadingOffset="-2.524414" valueClass="java.lang.Integer">
			<reportElement uuid="9f9fefa2-eee1-4f3e-9956-c66d37e34e00" x="137" y="290" width="100" height="20" origin="4" srcId="12"/>
			<textContent><![CDATA[21]]></textContent>
		</text>
		<text textHeight="12.578125" lineSpacingFactor="1.2578125" leadingOffset="-2.524414" valueClass="java.lang.Integer">
			<reportElement uuid="e96a05ce-cdb9-4ee9-8e21-a371d7a53279" x="375" y="290" width="100" height="20" origin="4" srcId="13"/>
			<textContent><![CDATA[10]]></textContent>
		</text>
		<text textHeight="12.578125" lineSpacingFactor="1.2578125" leadingOffset="-2.524414" valueClass="java.lang.Float">
			<reportElement uuid="09dae523-39b7-4d38-93f8-c1f4e214fea8" x="521" y="290" width="100" height="20" origin="4" srcId="14"/>
			<textContent><![CDATA[772348.0]]></textContent>
		</text>
		<text textHeight="12.578125" lineSpacingFactor="1.2578125" leadingOffset="-2.524414">
			<reportElement uuid="f113d5ad-3f73-400a-938d-ae09cc30d3c5" x="21" y="415" width="100" height="20" origin="4" srcId="10"/>
			<textContent><![CDATA[Uli Finkelstein]]></textContent>
		</text>
		<text textHeight="12.578125" lineSpacingFactor="1.2578125" leadingOffset="-2.524414" valueClass="java.lang.Integer">
			<reportElement uuid="a1803140-cd56-49d0-915e-b4cdeee35f68" x="252" y="415" width="100" height="20" origin="4" srcId="11"/>
			<textContent><![CDATA[276]]></textContent>
		</text>
		<text textHeight="12.578125" lineSpacingFactor="1.2578125" leadingOffset="-2.524414" valueClass="java.lang.Integer">
			<reportElement uuid="9f9fefa2-eee1-4f3e-9956-c66d37e34e00" x="137" y="415" width="100" height="20" origin="4" srcId="12"/>
			<textContent><![CDATA[42]]></textContent>
		</text>
		<text textHeight="12.578125" lineSpacingFactor="1.2578125" leadingOffset="-2.524414" valueClass="java.lang.Integer">
			<reportElement uuid="e96a05ce-cdb9-4ee9-8e21-a371d7a53279" x="375" y="415" width="100" height="20" origin="4" srcId="13"/>
			<textContent><![CDATA[43]]></textContent>
		</text>
		<text textHeight="12.578125" lineSpacingFactor="1.2578125" leadingOffset="-2.524414" valueClass="java.lang.Float">
			<reportElement uuid="09dae523-39b7-4d38-93f8-c1f4e214fea8" x="521" y="415" width="100" height="20" origin="4" srcId="14"/>
			<textContent><![CDATA[1990850.0]]></textContent>
		</text>
		<text textHeight="12.578125" lineSpacingFactor="1.2578125" leadingOffset="-2.524414">
			<reportElement uuid="f113d5ad-3f73-400a-938d-ae09cc30d3c5" x="21" y="540" width="100" height="20" origin="4" srcId="10"/>
			<textContent><![CDATA[Goldina Luckner]]></textContent>
		</text>
		<text textHeight="12.578125" lineSpacingFactor="1.2578125" leadingOffset="-2.524414" valueClass="java.lang.Integer">
			<reportElement uuid="a1803140-cd56-49d0-915e-b4cdeee35f68" x="252" y="540" width="100" height="20" origin="4" srcId="11"/>
			<textContent><![CDATA[524]]></textContent>
		</text>
		<text textHeight="12.578125" lineSpacingFactor="1.2578125" leadingOffset="-2.524414" valueClass="java.lang.Integer">
			<reportElement uuid="9f9fefa2-eee1-4f3e-9956-c66d37e34e00" x="137" y="540" width="100" height="20" origin="4" srcId="12"/>
			<textContent><![CDATA[3]]></textContent>
		</text>
		<text textHeight="12.578125" lineSpacingFactor="1.2578125" leadingOffset="-2.524414" valueClass="java.lang.Integer">
			<reportElement uuid="e96a05ce-cdb9-4ee9-8e21-a371d7a53279" x="375" y="540" width="100" height="20" origin="4" srcId="13"/>
			<textContent><![CDATA[47]]></textContent>
		</text>
		<text textHeight="12.578125" lineSpacingFactor="1.2578125" leadingOffset="-2.524414" valueClass="java.lang.Float">
			<reportElement uuid="09dae523-39b7-4d38-93f8-c1f4e214fea8" x="521" y="540" width="100" height="20" origin="4" srcId="14"/>
			<textContent><![CDATA[402639.0]]></textContent>
		</text>
	</page>
	<page>
		<line>
			<reportElement uuid="27275c97-40e2-4939-8900-7574da372a65" x="20" y="93" width="555" height="1" origin="3" srcId="4"/>
		</line>
		<text textHeight="12.578125" lineSpacingFactor="1.2578125" leadingOffset="-2.524414">
			<reportElement uuid="e83b38b2-0c41-4e74-ad13-0a4c8a94c51b" x="21" y="74" width="100" height="20" origin="3" srcId="5"/>
			<font isBold="true"/>
			<textContent><![CDATA[Proveedor]]></textContent>
		</text>
		<text textHeight="12.578125" lineSpacingFactor="1.2578125" leadingOffset="-2.524414">
			<reportElement uuid="530ce9ef-a10f-4700-b00a-4ead60aebb85" x="252" y="73" width="100" height="20" origin="3" srcId="6"/>
			<font isBold="true"/>
			<textContent><![CDATA[Código postal]]></textContent>
		</text>
		<text textHeight="12.578125" lineSpacingFactor="1.2578125" leadingOffset="-2.524414">
			<reportElement uuid="132e4a73-1ca8-4139-9e8c-c0142ad86571" x="137" y="73" width="100" height="20" origin="3" srcId="7"/>
			<font isBold="true"/>
			<textContent><![CDATA[Empleado]]></textContent>
		</text>
		<text textHeight="12.578125" lineSpacingFactor="1.2578125" leadingOffset="-2.524414">
			<reportElement uuid="1ce41270-2a0f-4f83-adbe-fd7fbfc19e7e" x="375" y="73" width="100" height="20" origin="3" srcId="8"/>
			<font isBold="true"/>
			<textContent><![CDATA[Producto]]></textContent>
		</text>
		<text textHeight="12.578125" lineSpacingFactor="1.2578125" leadingOffset="-2.524414">
			<reportElement uuid="bdc6ba74-6f4c-4ecf-98ba-ab21b873471a" x="521" y="73" width="100" height="20" origin="3" srcId="9"/>
			<font isBold="true"/>
			<textContent><![CDATA[TOTAL]]></textContent>
		</text>
		<text textHeight="12.578125" lineSpacingFactor="1.2578125" leadingOffset="-2.524414">
			<reportElement uuid="f113d5ad-3f73-400a-938d-ae09cc30d3c5" x="21" y="165" width="100" height="20" origin="4" srcId="10"/>
			<textContent><![CDATA[Peider Vogt]]></textContent>
		</text>
		<text textHeight="12.578125" lineSpacingFactor="1.2578125" leadingOffset="-2.524414" valueClass="java.lang.Integer">
			<reportElement uuid="a1803140-cd56-49d0-915e-b4cdeee35f68" x="252" y="165" width="100" height="20" origin="4" srcId="11"/>
			<textContent><![CDATA[8]]></textContent>
		</text>
		<text textHeight="12.578125" lineSpacingFactor="1.2578125" leadingOffset="-2.524414" valueClass="java.lang.Integer">
			<reportElement uuid="9f9fefa2-eee1-4f3e-9956-c66d37e34e00" x="137" y="165" width="100" height="20" origin="4" srcId="12"/>
			<textContent><![CDATA[5]]></textContent>
		</text>
		<text textHeight="12.578125" lineSpacingFactor="1.2578125" leadingOffset="-2.524414" valueClass="java.lang.Integer">
			<reportElement uuid="e96a05ce-cdb9-4ee9-8e21-a371d7a53279" x="375" y="165" width="100" height="20" origin="4" srcId="13"/>
			<textContent><![CDATA[23]]></textContent>
		</text>
		<text textHeight="12.578125" lineSpacingFactor="1.2578125" leadingOffset="-2.524414" valueClass="java.lang.Float">
			<reportElement uuid="09dae523-39b7-4d38-93f8-c1f4e214fea8" x="521" y="165" width="100" height="20" origin="4" srcId="14"/>
			<textContent><![CDATA[5766080.0]]></textContent>
		</text>
		<text textHeight="12.578125" lineSpacingFactor="1.2578125" leadingOffset="-2.524414">
			<reportElement uuid="f113d5ad-3f73-400a-938d-ae09cc30d3c5" x="21" y="290" width="100" height="20" origin="4" srcId="10"/>
			<textContent><![CDATA[Lusia Kraft]]></textContent>
		</text>
		<text textHeight="12.578125" lineSpacingFactor="1.2578125" leadingOffset="-2.524414" valueClass="java.lang.Integer">
			<reportElement uuid="a1803140-cd56-49d0-915e-b4cdeee35f68" x="252" y="290" width="100" height="20" origin="4" srcId="11"/>
			<textContent><![CDATA[203]]></textContent>
		</text>
		<text textHeight="12.578125" lineSpacingFactor="1.2578125" leadingOffset="-2.524414" valueClass="java.lang.Integer">
			<reportElement uuid="9f9fefa2-eee1-4f3e-9956-c66d37e34e00" x="137" y="290" width="100" height="20" origin="4" srcId="12"/>
			<textContent><![CDATA[24]]></textContent>
		</text>
		<text textHeight="12.578125" lineSpacingFactor="1.2578125" leadingOffset="-2.524414" valueClass="java.lang.Integer">
			<reportElement uuid="e96a05ce-cdb9-4ee9-8e21-a371d7a53279" x="375" y="290" width="100" height="20" origin="4" srcId="13"/>
			<textContent><![CDATA[8]]></textContent>
		</text>
		<text textHeight="12.578125" lineSpacingFactor="1.2578125" leadingOffset="-2.524414" valueClass="java.lang.Float">
			<reportElement uuid="09dae523-39b7-4d38-93f8-c1f4e214fea8" x="521" y="290" width="100" height="20" origin="4" srcId="14"/>
			<textContent><![CDATA[6560430.0]]></textContent>
		</text>
		<text textHeight="12.578125" lineSpacingFactor="1.2578125" leadingOffset="-2.524414">
			<reportElement uuid="f113d5ad-3f73-400a-938d-ae09cc30d3c5" x="21" y="415" width="100" height="20" origin="4" srcId="10"/>
			<textContent><![CDATA[Finjas Mager]]></textContent>
		</text>
		<text textHeight="12.578125" lineSpacingFactor="1.2578125" leadingOffset="-2.524414" valueClass="java.lang.Integer">
			<reportElement uuid="a1803140-cd56-49d0-915e-b4cdeee35f68" x="252" y="415" width="100" height="20" origin="4" srcId="11"/>
			<textContent><![CDATA[702]]></textContent>
		</text>
		<text textHeight="12.578125" lineSpacingFactor="1.2578125" leadingOffset="-2.524414" valueClass="java.lang.Integer">
			<reportElement uuid="9f9fefa2-eee1-4f3e-9956-c66d37e34e00" x="137" y="415" width="100" height="20" origin="4" srcId="12"/>
			<textContent><![CDATA[33]]></textContent>
		</text>
		<text textHeight="12.578125" lineSpacingFactor="1.2578125" leadingOffset="-2.524414" valueClass="java.lang.Integer">
			<reportElement uuid="e96a05ce-cdb9-4ee9-8e21-a371d7a53279" x="375" y="415" width="100" height="20" origin="4" srcId="13"/>
			<textContent><![CDATA[32]]></textContent>
		</text>
		<text textHeight="12.578125" lineSpacingFactor="1.2578125" leadingOffset="-2.524414" valueClass="java.lang.Float">
			<reportElement uuid="09dae523-39b7-4d38-93f8-c1f4e214fea8" x="521" y="415" width="100" height="20" origin="4" srcId="14"/>
			<textContent><![CDATA[3245590.0]]></textContent>
		</text>
		<text textHeight="12.578125" lineSpacingFactor="1.2578125" leadingOffset="-2.1972656">
			<reportElement uuid="f113d5ad-3f73-400a-938d-ae09cc30d3c5" x="21" y="540" width="100" height="20" origin="4" srcId="10"/>
			<textContent><![CDATA[Otger ]]></textContent>
		</text>
		<text textHeight="12.578125" lineSpacingFactor="1.2578125" leadingOffset="-2.524414" valueClass="java.lang.Integer">
			<reportElement uuid="a1803140-cd56-49d0-915e-b4cdeee35f68" x="252" y="540" width="100" height="20" origin="4" srcId="11"/>
			<textContent><![CDATA[882]]></textContent>
		</text>
		<text textHeight="12.578125" lineSpacingFactor="1.2578125" leadingOffset="-2.524414" valueClass="java.lang.Integer">
			<reportElement uuid="9f9fefa2-eee1-4f3e-9956-c66d37e34e00" x="137" y="540" width="100" height="20" origin="4" srcId="12"/>
			<textContent><![CDATA[33]]></textContent>
		</text>
		<text textHeight="12.578125" lineSpacingFactor="1.2578125" leadingOffset="-2.524414" valueClass="java.lang.Integer">
			<reportElement uuid="e96a05ce-cdb9-4ee9-8e21-a371d7a53279" x="375" y="540" width="100" height="20" origin="4" srcId="13"/>
			<textContent><![CDATA[45]]></textContent>
		</text>
		<text textHeight="12.578125" lineSpacingFactor="1.2578125" leadingOffset="-2.524414" valueClass="java.lang.Float">
			<reportElement uuid="09dae523-39b7-4d38-93f8-c1f4e214fea8" x="521" y="540" width="100" height="20" origin="4" srcId="14"/>
			<textContent><![CDATA[3696910.0]]></textContent>
		</text>
	</page>
	<page>
		<line>
			<reportElement uuid="27275c97-40e2-4939-8900-7574da372a65" x="20" y="93" width="555" height="1" origin="3" srcId="4"/>
		</line>
		<text textHeight="12.578125" lineSpacingFactor="1.2578125" leadingOffset="-2.524414">
			<reportElement uuid="e83b38b2-0c41-4e74-ad13-0a4c8a94c51b" x="21" y="74" width="100" height="20" origin="3" srcId="5"/>
			<font isBold="true"/>
			<textContent><![CDATA[Proveedor]]></textContent>
		</text>
		<text textHeight="12.578125" lineSpacingFactor="1.2578125" leadingOffset="-2.524414">
			<reportElement uuid="530ce9ef-a10f-4700-b00a-4ead60aebb85" x="252" y="73" width="100" height="20" origin="3" srcId="6"/>
			<font isBold="true"/>
			<textContent><![CDATA[Código postal]]></textContent>
		</text>
		<text textHeight="12.578125" lineSpacingFactor="1.2578125" leadingOffset="-2.524414">
			<reportElement uuid="132e4a73-1ca8-4139-9e8c-c0142ad86571" x="137" y="73" width="100" height="20" origin="3" srcId="7"/>
			<font isBold="true"/>
			<textContent><![CDATA[Empleado]]></textContent>
		</text>
		<text textHeight="12.578125" lineSpacingFactor="1.2578125" leadingOffset="-2.524414">
			<reportElement uuid="1ce41270-2a0f-4f83-adbe-fd7fbfc19e7e" x="375" y="73" width="100" height="20" origin="3" srcId="8"/>
			<font isBold="true"/>
			<textContent><![CDATA[Producto]]></textContent>
		</text>
		<text textHeight="12.578125" lineSpacingFactor="1.2578125" leadingOffset="-2.524414">
			<reportElement uuid="bdc6ba74-6f4c-4ecf-98ba-ab21b873471a" x="521" y="73" width="100" height="20" origin="3" srcId="9"/>
			<font isBold="true"/>
			<textContent><![CDATA[TOTAL]]></textContent>
		</text>
		<text textHeight="12.578125" lineSpacingFactor="1.2578125" leadingOffset="-2.524414">
			<reportElement uuid="f113d5ad-3f73-400a-938d-ae09cc30d3c5" x="21" y="165" width="100" height="20" origin="4" srcId="10"/>
			<textContent><![CDATA[Maxerus Fellendorf]]></textContent>
		</text>
		<text textHeight="12.578125" lineSpacingFactor="1.2578125" leadingOffset="-2.524414" valueClass="java.lang.Integer">
			<reportElement uuid="a1803140-cd56-49d0-915e-b4cdeee35f68" x="252" y="165" width="100" height="20" origin="4" srcId="11"/>
			<textContent><![CDATA[36]]></textContent>
		</text>
		<text textHeight="12.578125" lineSpacingFactor="1.2578125" leadingOffset="-2.524414" valueClass="java.lang.Integer">
			<reportElement uuid="9f9fefa2-eee1-4f3e-9956-c66d37e34e00" x="137" y="165" width="100" height="20" origin="4" srcId="12"/>
			<textContent><![CDATA[4]]></textContent>
		</text>
		<text textHeight="12.578125" lineSpacingFactor="1.2578125" leadingOffset="-2.524414" valueClass="java.lang.Integer">
			<reportElement uuid="e96a05ce-cdb9-4ee9-8e21-a371d7a53279" x="375" y="165" width="100" height="20" origin="4" srcId="13"/>
			<textContent><![CDATA[1]]></textContent>
		</text>
		<text textHeight="12.578125" lineSpacingFactor="1.2578125" leadingOffset="-2.524414" valueClass="java.lang.Float">
			<reportElement uuid="09dae523-39b7-4d38-93f8-c1f4e214fea8" x="521" y="165" width="100" height="20" origin="4" srcId="14"/>
			<textContent><![CDATA[895032.0]]></textContent>
		</text>
		<text textHeight="12.578125" lineSpacingFactor="1.2578125" leadingOffset="-2.524414">
			<reportElement uuid="f113d5ad-3f73-400a-938d-ae09cc30d3c5" x="21" y="290" width="100" height="20" origin="4" srcId="10"/>
			<textContent><![CDATA[Mayen Heinemann]]></textContent>
		</text>
		<text textHeight="12.578125" lineSpacingFactor="1.2578125" leadingOffset="-2.524414" valueClass="java.lang.Integer">
			<reportElement uuid="a1803140-cd56-49d0-915e-b4cdeee35f68" x="252" y="290" width="100" height="20" origin="4" srcId="11"/>
			<textContent><![CDATA[4]]></textContent>
		</text>
		<text textHeight="12.578125" lineSpacingFactor="1.2578125" leadingOffset="-2.524414" valueClass="java.lang.Integer">
			<reportElement uuid="9f9fefa2-eee1-4f3e-9956-c66d37e34e00" x="137" y="290" width="100" height="20" origin="4" srcId="12"/>
			<textContent><![CDATA[32]]></textContent>
		</text>
		<text textHeight="12.578125" lineSpacingFactor="1.2578125" leadingOffset="-2.524414" valueClass="java.lang.Integer">
			<reportElement uuid="e96a05ce-cdb9-4ee9-8e21-a371d7a53279" x="375" y="290" width="100" height="20" origin="4" srcId="13"/>
			<textContent><![CDATA[36]]></textContent>
		</text>
		<text textHeight="12.578125" lineSpacingFactor="1.2578125" leadingOffset="-2.524414" valueClass="java.lang.Float">
			<reportElement uuid="09dae523-39b7-4d38-93f8-c1f4e214fea8" x="521" y="290" width="100" height="20" origin="4" srcId="14"/>
			<textContent><![CDATA[2352410.0]]></textContent>
		</text>
		<text textHeight="12.578125" lineSpacingFactor="1.2578125" leadingOffset="-2.524414">
			<reportElement uuid="f113d5ad-3f73-400a-938d-ae09cc30d3c5" x="21" y="415" width="100" height="20" origin="4" srcId="10"/>
			<textContent><![CDATA[Bj├Ârke Dautzenberg]]></textContent>
		</text>
		<text textHeight="12.578125" lineSpacingFactor="1.2578125" leadingOffset="-2.524414" valueClass="java.lang.Integer">
			<reportElement uuid="a1803140-cd56-49d0-915e-b4cdeee35f68" x="252" y="415" width="100" height="20" origin="4" srcId="11"/>
			<textContent><![CDATA[752]]></textContent>
		</text>
		<text textHeight="12.578125" lineSpacingFactor="1.2578125" leadingOffset="-2.524414" valueClass="java.lang.Integer">
			<reportElement uuid="9f9fefa2-eee1-4f3e-9956-c66d37e34e00" x="137" y="415" width="100" height="20" origin="4" srcId="12"/>
			<textContent><![CDATA[22]]></textContent>
		</text>
		<text textHeight="12.578125" lineSpacingFactor="1.2578125" leadingOffset="-2.524414" valueClass="java.lang.Integer">
			<reportElement uuid="e96a05ce-cdb9-4ee9-8e21-a371d7a53279" x="375" y="415" width="100" height="20" origin="4" srcId="13"/>
			<textContent><![CDATA[8]]></textContent>
		</text>
		<text textHeight="12.578125" lineSpacingFactor="1.2578125" leadingOffset="-2.524414" valueClass="java.lang.Float">
			<reportElement uuid="09dae523-39b7-4d38-93f8-c1f4e214fea8" x="521" y="415" width="100" height="20" origin="4" srcId="14"/>
			<textContent><![CDATA[7236640.0]]></textContent>
		</text>
		<text textHeight="12.578125" lineSpacingFactor="1.2578125" leadingOffset="-2.524414">
			<reportElement uuid="f113d5ad-3f73-400a-938d-ae09cc30d3c5" x="21" y="540" width="100" height="20" origin="4" srcId="10"/>
			<textContent><![CDATA[Lisandra Anger]]></textContent>
		</text>
		<text textHeight="12.578125" lineSpacingFactor="1.2578125" leadingOffset="-2.524414" valueClass="java.lang.Integer">
			<reportElement uuid="a1803140-cd56-49d0-915e-b4cdeee35f68" x="252" y="540" width="100" height="20" origin="4" srcId="11"/>
			<textContent><![CDATA[320]]></textContent>
		</text>
		<text textHeight="12.578125" lineSpacingFactor="1.2578125" leadingOffset="-2.524414" valueClass="java.lang.Integer">
			<reportElement uuid="9f9fefa2-eee1-4f3e-9956-c66d37e34e00" x="137" y="540" width="100" height="20" origin="4" srcId="12"/>
			<textContent><![CDATA[23]]></textContent>
		</text>
		<text textHeight="12.578125" lineSpacingFactor="1.2578125" leadingOffset="-2.524414" valueClass="java.lang.Integer">
			<reportElement uuid="e96a05ce-cdb9-4ee9-8e21-a371d7a53279" x="375" y="540" width="100" height="20" origin="4" srcId="13"/>
			<textContent><![CDATA[12]]></textContent>
		</text>
		<text textHeight="12.578125" lineSpacingFactor="1.2578125" leadingOffset="-2.524414" valueClass="java.lang.Float">
			<reportElement uuid="09dae523-39b7-4d38-93f8-c1f4e214fea8" x="521" y="540" width="100" height="20" origin="4" srcId="14"/>
			<textContent><![CDATA[2234190.0]]></textContent>
		</text>
	</page>
	<page>
		<line>
			<reportElement uuid="27275c97-40e2-4939-8900-7574da372a65" x="20" y="93" width="555" height="1" origin="3" srcId="4"/>
		</line>
		<text textHeight="12.578125" lineSpacingFactor="1.2578125" leadingOffset="-2.524414">
			<reportElement uuid="e83b38b2-0c41-4e74-ad13-0a4c8a94c51b" x="21" y="74" width="100" height="20" origin="3" srcId="5"/>
			<font isBold="true"/>
			<textContent><![CDATA[Proveedor]]></textContent>
		</text>
		<text textHeight="12.578125" lineSpacingFactor="1.2578125" leadingOffset="-2.524414">
			<reportElement uuid="530ce9ef-a10f-4700-b00a-4ead60aebb85" x="252" y="73" width="100" height="20" origin="3" srcId="6"/>
			<font isBold="true"/>
			<textContent><![CDATA[Código postal]]></textContent>
		</text>
		<text textHeight="12.578125" lineSpacingFactor="1.2578125" leadingOffset="-2.524414">
			<reportElement uuid="132e4a73-1ca8-4139-9e8c-c0142ad86571" x="137" y="73" width="100" height="20" origin="3" srcId="7"/>
			<font isBold="true"/>
			<textContent><![CDATA[Empleado]]></textContent>
		</text>
		<text textHeight="12.578125" lineSpacingFactor="1.2578125" leadingOffset="-2.524414">
			<reportElement uuid="1ce41270-2a0f-4f83-adbe-fd7fbfc19e7e" x="375" y="73" width="100" height="20" origin="3" srcId="8"/>
			<font isBold="true"/>
			<textContent><![CDATA[Producto]]></textContent>
		</text>
		<text textHeight="12.578125" lineSpacingFactor="1.2578125" leadingOffset="-2.524414">
			<reportElement uuid="bdc6ba74-6f4c-4ecf-98ba-ab21b873471a" x="521" y="73" width="100" height="20" origin="3" srcId="9"/>
			<font isBold="true"/>
			<textContent><![CDATA[TOTAL]]></textContent>
		</text>
		<text textHeight="12.578125" lineSpacingFactor="1.2578125" leadingOffset="-2.524414">
			<reportElement uuid="f113d5ad-3f73-400a-938d-ae09cc30d3c5" x="21" y="165" width="100" height="20" origin="4" srcId="10"/>
			<textContent><![CDATA[Kuno Husemann]]></textContent>
		</text>
		<text textHeight="12.578125" lineSpacingFactor="1.2578125" leadingOffset="-2.524414" valueClass="java.lang.Integer">
			<reportElement uuid="a1803140-cd56-49d0-915e-b4cdeee35f68" x="252" y="165" width="100" height="20" origin="4" srcId="11"/>
			<textContent><![CDATA[792]]></textContent>
		</text>
		<text textHeight="12.578125" lineSpacingFactor="1.2578125" leadingOffset="-2.524414" valueClass="java.lang.Integer">
			<reportElement uuid="9f9fefa2-eee1-4f3e-9956-c66d37e34e00" x="137" y="165" width="100" height="20" origin="4" srcId="12"/>
			<textContent><![CDATA[47]]></textContent>
		</text>
		<text textHeight="12.578125" lineSpacingFactor="1.2578125" leadingOffset="-2.524414" valueClass="java.lang.Integer">
			<reportElement uuid="e96a05ce-cdb9-4ee9-8e21-a371d7a53279" x="375" y="165" width="100" height="20" origin="4" srcId="13"/>
			<textContent><![CDATA[24]]></textContent>
		</text>
		<text textHeight="12.578125" lineSpacingFactor="1.2578125" leadingOffset="-2.524414" valueClass="java.lang.Float">
			<reportElement uuid="09dae523-39b7-4d38-93f8-c1f4e214fea8" x="521" y="165" width="100" height="20" origin="4" srcId="14"/>
			<textContent><![CDATA[8113890.0]]></textContent>
		</text>
		<text textHeight="12.578125" lineSpacingFactor="1.2578125" leadingOffset="-2.524414">
			<reportElement uuid="f113d5ad-3f73-400a-938d-ae09cc30d3c5" x="21" y="290" width="100" height="20" origin="4" srcId="10"/>
			<textContent><![CDATA[R├╝der chr├Âder]]></textContent>
		</text>
		<text textHeight="12.578125" lineSpacingFactor="1.2578125" leadingOffset="-2.524414" valueClass="java.lang.Integer">
			<reportElement uuid="a1803140-cd56-49d0-915e-b4cdeee35f68" x="252" y="290" width="100" height="20" origin="4" srcId="11"/>
			<textContent><![CDATA[400]]></textContent>
		</text>
		<text textHeight="12.578125" lineSpacingFactor="1.2578125" leadingOffset="-2.524414" valueClass="java.lang.Integer">
			<reportElement uuid="9f9fefa2-eee1-4f3e-9956-c66d37e34e00" x="137" y="290" width="100" height="20" origin="4" srcId="12"/>
			<textContent><![CDATA[13]]></textContent>
		</text>
		<text textHeight="12.578125" lineSpacingFactor="1.2578125" leadingOffset="-2.524414" valueClass="java.lang.Integer">
			<reportElement uuid="e96a05ce-cdb9-4ee9-8e21-a371d7a53279" x="375" y="290" width="100" height="20" origin="4" srcId="13"/>
			<textContent><![CDATA[27]]></textContent>
		</text>
		<text textHeight="12.578125" lineSpacingFactor="1.2578125" leadingOffset="-2.524414" valueClass="java.lang.Float">
			<reportElement uuid="09dae523-39b7-4d38-93f8-c1f4e214fea8" x="521" y="290" width="100" height="20" origin="4" srcId="14"/>
			<textContent><![CDATA[3204940.0]]></textContent>
		</text>
		<text textHeight="12.578125" lineSpacingFactor="1.2578125" leadingOffset="-2.524414">
			<reportElement uuid="f113d5ad-3f73-400a-938d-ae09cc30d3c5" x="21" y="415" width="100" height="20" origin="4" srcId="10"/>
			<textContent><![CDATA[Ablona  Klemperer]]></textContent>
		</text>
		<text textHeight="12.578125" lineSpacingFactor="1.2578125" leadingOffset="-2.524414" valueClass="java.lang.Integer">
			<reportElement uuid="a1803140-cd56-49d0-915e-b4cdeee35f68" x="252" y="415" width="100" height="20" origin="4" srcId="11"/>
			<textContent><![CDATA[250]]></textContent>
		</text>
		<text textHeight="12.578125" lineSpacingFactor="1.2578125" leadingOffset="-2.524414" valueClass="java.lang.Integer">
			<reportElement uuid="9f9fefa2-eee1-4f3e-9956-c66d37e34e00" x="137" y="415" width="100" height="20" origin="4" srcId="12"/>
			<textContent><![CDATA[41]]></textContent>
		</text>
		<text textHeight="12.578125" lineSpacingFactor="1.2578125" leadingOffset="-2.524414" valueClass="java.lang.Integer">
			<reportElement uuid="e96a05ce-cdb9-4ee9-8e21-a371d7a53279" x="375" y="415" width="100" height="20" origin="4" srcId="13"/>
			<textContent><![CDATA[34]]></textContent>
		</text>
		<text textHeight="12.578125" lineSpacingFactor="1.2578125" leadingOffset="-2.524414" valueClass="java.lang.Float">
			<reportElement uuid="09dae523-39b7-4d38-93f8-c1f4e214fea8" x="521" y="415" width="100" height="20" origin="4" srcId="14"/>
			<textContent><![CDATA[2211440.0]]></textContent>
		</text>
		<text textHeight="12.578125" lineSpacingFactor="1.2578125" leadingOffset="-2.524414">
			<reportElement uuid="f113d5ad-3f73-400a-938d-ae09cc30d3c5" x="21" y="540" width="100" height="20" origin="4" srcId="10"/>
			<textContent><![CDATA[Hieronymus Stein]]></textContent>
		</text>
		<text textHeight="12.578125" lineSpacingFactor="1.2578125" leadingOffset="-2.524414" valueClass="java.lang.Integer">
			<reportElement uuid="a1803140-cd56-49d0-915e-b4cdeee35f68" x="252" y="540" width="100" height="20" origin="4" srcId="11"/>
			<textContent><![CDATA[268]]></textContent>
		</text>
		<text textHeight="12.578125" lineSpacingFactor="1.2578125" leadingOffset="-2.524414" valueClass="java.lang.Integer">
			<reportElement uuid="9f9fefa2-eee1-4f3e-9956-c66d37e34e00" x="137" y="540" width="100" height="20" origin="4" srcId="12"/>
			<textContent><![CDATA[40]]></textContent>
		</text>
		<text textHeight="12.578125" lineSpacingFactor="1.2578125" leadingOffset="-2.524414" valueClass="java.lang.Integer">
			<reportElement uuid="e96a05ce-cdb9-4ee9-8e21-a371d7a53279" x="375" y="540" width="100" height="20" origin="4" srcId="13"/>
			<textContent><![CDATA[15]]></textContent>
		</text>
		<text textHeight="12.578125" lineSpacingFactor="1.2578125" leadingOffset="-2.524414" valueClass="java.lang.Float">
			<reportElement uuid="09dae523-39b7-4d38-93f8-c1f4e214fea8" x="521" y="540" width="100" height="20" origin="4" srcId="14"/>
			<textContent><![CDATA[9641760.0]]></textContent>
		</text>
	</page>
	<page>
		<line>
			<reportElement uuid="27275c97-40e2-4939-8900-7574da372a65" x="20" y="93" width="555" height="1" origin="3" srcId="4"/>
		</line>
		<text textHeight="12.578125" lineSpacingFactor="1.2578125" leadingOffset="-2.524414">
			<reportElement uuid="e83b38b2-0c41-4e74-ad13-0a4c8a94c51b" x="21" y="74" width="100" height="20" origin="3" srcId="5"/>
			<font isBold="true"/>
			<textContent><![CDATA[Proveedor]]></textContent>
		</text>
		<text textHeight="12.578125" lineSpacingFactor="1.2578125" leadingOffset="-2.524414">
			<reportElement uuid="530ce9ef-a10f-4700-b00a-4ead60aebb85" x="252" y="73" width="100" height="20" origin="3" srcId="6"/>
			<font isBold="true"/>
			<textContent><![CDATA[Código postal]]></textContent>
		</text>
		<text textHeight="12.578125" lineSpacingFactor="1.2578125" leadingOffset="-2.524414">
			<reportElement uuid="132e4a73-1ca8-4139-9e8c-c0142ad86571" x="137" y="73" width="100" height="20" origin="3" srcId="7"/>
			<font isBold="true"/>
			<textContent><![CDATA[Empleado]]></textContent>
		</text>
		<text textHeight="12.578125" lineSpacingFactor="1.2578125" leadingOffset="-2.524414">
			<reportElement uuid="1ce41270-2a0f-4f83-adbe-fd7fbfc19e7e" x="375" y="73" width="100" height="20" origin="3" srcId="8"/>
			<font isBold="true"/>
			<textContent><![CDATA[Producto]]></textContent>
		</text>
		<text textHeight="12.578125" lineSpacingFactor="1.2578125" leadingOffset="-2.524414">
			<reportElement uuid="bdc6ba74-6f4c-4ecf-98ba-ab21b873471a" x="521" y="73" width="100" height="20" origin="3" srcId="9"/>
			<font isBold="true"/>
			<textContent><![CDATA[TOTAL]]></textContent>
		</text>
		<text textHeight="12.578125" lineSpacingFactor="1.2578125" leadingOffset="-2.524414">
			<reportElement uuid="f113d5ad-3f73-400a-938d-ae09cc30d3c5" x="21" y="165" width="100" height="20" origin="4" srcId="10"/>
			<textContent><![CDATA[Wolfrad Feierbach]]></textContent>
		</text>
		<text textHeight="12.578125" lineSpacingFactor="1.2578125" leadingOffset="-2.524414" valueClass="java.lang.Integer">
			<reportElement uuid="a1803140-cd56-49d0-915e-b4cdeee35f68" x="252" y="165" width="100" height="20" origin="4" srcId="11"/>
			<textContent><![CDATA[32]]></textContent>
		</text>
		<text textHeight="12.578125" lineSpacingFactor="1.2578125" leadingOffset="-2.524414" valueClass="java.lang.Integer">
			<reportElement uuid="9f9fefa2-eee1-4f3e-9956-c66d37e34e00" x="137" y="165" width="100" height="20" origin="4" srcId="12"/>
			<textContent><![CDATA[37]]></textContent>
		</text>
		<text textHeight="12.578125" lineSpacingFactor="1.2578125" leadingOffset="-2.524414" valueClass="java.lang.Integer">
			<reportElement uuid="e96a05ce-cdb9-4ee9-8e21-a371d7a53279" x="375" y="165" width="100" height="20" origin="4" srcId="13"/>
			<textContent><![CDATA[12]]></textContent>
		</text>
		<text textHeight="12.578125" lineSpacingFactor="1.2578125" leadingOffset="-2.524414" valueClass="java.lang.Float">
			<reportElement uuid="09dae523-39b7-4d38-93f8-c1f4e214fea8" x="521" y="165" width="100" height="20" origin="4" srcId="14"/>
			<textContent><![CDATA[8728140.0]]></textContent>
		</text>
		<text textHeight="12.578125" lineSpacingFactor="1.2578125" leadingOffset="-2.524414">
			<reportElement uuid="f113d5ad-3f73-400a-938d-ae09cc30d3c5" x="21" y="290" width="100" height="20" origin="4" srcId="10"/>
			<textContent><![CDATA[Kosmea verbeck]]></textContent>
		</text>
		<text textHeight="12.578125" lineSpacingFactor="1.2578125" leadingOffset="-2.524414" valueClass="java.lang.Integer">
			<reportElement uuid="a1803140-cd56-49d0-915e-b4cdeee35f68" x="252" y="290" width="100" height="20" origin="4" srcId="11"/>
			<textContent><![CDATA[400]]></textContent>
		</text>
		<text textHeight="12.578125" lineSpacingFactor="1.2578125" leadingOffset="-2.524414" valueClass="java.lang.Integer">
			<reportElement uuid="9f9fefa2-eee1-4f3e-9956-c66d37e34e00" x="137" y="290" width="100" height="20" origin="4" srcId="12"/>
			<textContent><![CDATA[47]]></textContent>
		</text>
		<text textHeight="12.578125" lineSpacingFactor="1.2578125" leadingOffset="-2.524414" valueClass="java.lang.Integer">
			<reportElement uuid="e96a05ce-cdb9-4ee9-8e21-a371d7a53279" x="375" y="290" width="100" height="20" origin="4" srcId="13"/>
			<textContent><![CDATA[21]]></textContent>
		</text>
		<text textHeight="12.578125" lineSpacingFactor="1.2578125" leadingOffset="-2.524414" valueClass="java.lang.Float">
			<reportElement uuid="09dae523-39b7-4d38-93f8-c1f4e214fea8" x="521" y="290" width="100" height="20" origin="4" srcId="14"/>
			<textContent><![CDATA[6990950.0]]></textContent>
		</text>
		<text textHeight="12.578125" lineSpacingFactor="1.2578125" leadingOffset="-2.524414">
			<reportElement uuid="f113d5ad-3f73-400a-938d-ae09cc30d3c5" x="21" y="415" width="100" height="20" origin="4" srcId="10"/>
			<textContent><![CDATA[Lejana omberg]]></textContent>
		</text>
		<text textHeight="12.578125" lineSpacingFactor="1.2578125" leadingOffset="-2.524414" valueClass="java.lang.Integer">
			<reportElement uuid="a1803140-cd56-49d0-915e-b4cdeee35f68" x="252" y="415" width="100" height="20" origin="4" srcId="11"/>
			<textContent><![CDATA[458]]></textContent>
		</text>
		<text textHeight="12.578125" lineSpacingFactor="1.2578125" leadingOffset="-2.524414" valueClass="java.lang.Integer">
			<reportElement uuid="9f9fefa2-eee1-4f3e-9956-c66d37e34e00" x="137" y="415" width="100" height="20" origin="4" srcId="12"/>
			<textContent><![CDATA[13]]></textContent>
		</text>
		<text textHeight="12.578125" lineSpacingFactor="1.2578125" leadingOffset="-2.524414" valueClass="java.lang.Integer">
			<reportElement uuid="e96a05ce-cdb9-4ee9-8e21-a371d7a53279" x="375" y="415" width="100" height="20" origin="4" srcId="13"/>
			<textContent><![CDATA[2]]></textContent>
		</text>
		<text textHeight="12.578125" lineSpacingFactor="1.2578125" leadingOffset="-2.524414" valueClass="java.lang.Float">
			<reportElement uuid="09dae523-39b7-4d38-93f8-c1f4e214fea8" x="521" y="415" width="100" height="20" origin="4" srcId="14"/>
			<textContent><![CDATA[2763020.0]]></textContent>
		</text>
		<text textHeight="12.578125" lineSpacingFactor="1.2578125" leadingOffset="-2.524414">
			<reportElement uuid="f113d5ad-3f73-400a-938d-ae09cc30d3c5" x="21" y="540" width="100" height="20" origin="4" srcId="10"/>
			<textContent><![CDATA[Baldo  Baade]]></textContent>
		</text>
		<text textHeight="12.578125" lineSpacingFactor="1.2578125" leadingOffset="-2.524414" valueClass="java.lang.Integer">
			<reportElement uuid="a1803140-cd56-49d0-915e-b4cdeee35f68" x="252" y="540" width="100" height="20" origin="4" srcId="11"/>
			<textContent><![CDATA[578]]></textContent>
		</text>
		<text textHeight="12.578125" lineSpacingFactor="1.2578125" leadingOffset="-2.524414" valueClass="java.lang.Integer">
			<reportElement uuid="9f9fefa2-eee1-4f3e-9956-c66d37e34e00" x="137" y="540" width="100" height="20" origin="4" srcId="12"/>
			<textContent><![CDATA[46]]></textContent>
		</text>
		<text textHeight="12.578125" lineSpacingFactor="1.2578125" leadingOffset="-2.524414" valueClass="java.lang.Integer">
			<reportElement uuid="e96a05ce-cdb9-4ee9-8e21-a371d7a53279" x="375" y="540" width="100" height="20" origin="4" srcId="13"/>
			<textContent><![CDATA[44]]></textContent>
		</text>
		<text textHeight="12.578125" lineSpacingFactor="1.2578125" leadingOffset="-2.524414" valueClass="java.lang.Float">
			<reportElement uuid="09dae523-39b7-4d38-93f8-c1f4e214fea8" x="521" y="540" width="100" height="20" origin="4" srcId="14"/>
			<textContent><![CDATA[7933200.0]]></textContent>
		</text>
	</page>
	<page>
		<line>
			<reportElement uuid="27275c97-40e2-4939-8900-7574da372a65" x="20" y="93" width="555" height="1" origin="3" srcId="4"/>
		</line>
		<text textHeight="12.578125" lineSpacingFactor="1.2578125" leadingOffset="-2.524414">
			<reportElement uuid="e83b38b2-0c41-4e74-ad13-0a4c8a94c51b" x="21" y="74" width="100" height="20" origin="3" srcId="5"/>
			<font isBold="true"/>
			<textContent><![CDATA[Proveedor]]></textContent>
		</text>
		<text textHeight="12.578125" lineSpacingFactor="1.2578125" leadingOffset="-2.524414">
			<reportElement uuid="530ce9ef-a10f-4700-b00a-4ead60aebb85" x="252" y="73" width="100" height="20" origin="3" srcId="6"/>
			<font isBold="true"/>
			<textContent><![CDATA[Código postal]]></textContent>
		</text>
		<text textHeight="12.578125" lineSpacingFactor="1.2578125" leadingOffset="-2.524414">
			<reportElement uuid="132e4a73-1ca8-4139-9e8c-c0142ad86571" x="137" y="73" width="100" height="20" origin="3" srcId="7"/>
			<font isBold="true"/>
			<textContent><![CDATA[Empleado]]></textContent>
		</text>
		<text textHeight="12.578125" lineSpacingFactor="1.2578125" leadingOffset="-2.524414">
			<reportElement uuid="1ce41270-2a0f-4f83-adbe-fd7fbfc19e7e" x="375" y="73" width="100" height="20" origin="3" srcId="8"/>
			<font isBold="true"/>
			<textContent><![CDATA[Producto]]></textContent>
		</text>
		<text textHeight="12.578125" lineSpacingFactor="1.2578125" leadingOffset="-2.524414">
			<reportElement uuid="bdc6ba74-6f4c-4ecf-98ba-ab21b873471a" x="521" y="73" width="100" height="20" origin="3" srcId="9"/>
			<font isBold="true"/>
			<textContent><![CDATA[TOTAL]]></textContent>
		</text>
		<text textHeight="12.578125" lineSpacingFactor="1.2578125" leadingOffset="-2.524414">
			<reportElement uuid="f113d5ad-3f73-400a-938d-ae09cc30d3c5" x="21" y="165" width="100" height="20" origin="4" srcId="10"/>
			<textContent><![CDATA[Farhild Freund]]></textContent>
		</text>
		<text textHeight="12.578125" lineSpacingFactor="1.2578125" leadingOffset="-2.524414" valueClass="java.lang.Integer">
			<reportElement uuid="a1803140-cd56-49d0-915e-b4cdeee35f68" x="252" y="165" width="100" height="20" origin="4" srcId="11"/>
			<textContent><![CDATA[76]]></textContent>
		</text>
		<text textHeight="12.578125" lineSpacingFactor="1.2578125" leadingOffset="-2.524414" valueClass="java.lang.Integer">
			<reportElement uuid="9f9fefa2-eee1-4f3e-9956-c66d37e34e00" x="137" y="165" width="100" height="20" origin="4" srcId="12"/>
			<textContent><![CDATA[19]]></textContent>
		</text>
		<text textHeight="12.578125" lineSpacingFactor="1.2578125" leadingOffset="-2.524414" valueClass="java.lang.Integer">
			<reportElement uuid="e96a05ce-cdb9-4ee9-8e21-a371d7a53279" x="375" y="165" width="100" height="20" origin="4" srcId="13"/>
			<textContent><![CDATA[17]]></textContent>
		</text>
		<text textHeight="12.578125" lineSpacingFactor="1.2578125" leadingOffset="-2.524414" valueClass="java.lang.Float">
			<reportElement uuid="09dae523-39b7-4d38-93f8-c1f4e214fea8" x="521" y="165" width="100" height="20" origin="4" srcId="14"/>
			<textContent><![CDATA[4071900.0]]></textContent>
		</text>
		<text textHeight="12.578125" lineSpacingFactor="1.2578125" leadingOffset="-2.524414">
			<reportElement uuid="f113d5ad-3f73-400a-938d-ae09cc30d3c5" x="21" y="290" width="100" height="20" origin="4" srcId="10"/>
			<textContent><![CDATA[Julitta Langmann]]></textContent>
		</text>
		<text textHeight="12.578125" lineSpacingFactor="1.2578125" leadingOffset="-2.524414" valueClass="java.lang.Integer">
			<reportElement uuid="a1803140-cd56-49d0-915e-b4cdeee35f68" x="252" y="290" width="100" height="20" origin="4" srcId="11"/>
			<textContent><![CDATA[616]]></textContent>
		</text>
		<text textHeight="12.578125" lineSpacingFactor="1.2578125" leadingOffset="-2.524414" valueClass="java.lang.Integer">
			<reportElement uuid="9f9fefa2-eee1-4f3e-9956-c66d37e34e00" x="137" y="290" width="100" height="20" origin="4" srcId="12"/>
			<textContent><![CDATA[28]]></textContent>
		</text>
		<text textHeight="12.578125" lineSpacingFactor="1.2578125" leadingOffset="-2.524414" valueClass="java.lang.Integer">
			<reportElement uuid="e96a05ce-cdb9-4ee9-8e21-a371d7a53279" x="375" y="290" width="100" height="20" origin="4" srcId="13"/>
			<textContent><![CDATA[9]]></textContent>
		</text>
		<text textHeight="12.578125" lineSpacingFactor="1.2578125" leadingOffset="-2.524414" valueClass="java.lang.Float">
			<reportElement uuid="09dae523-39b7-4d38-93f8-c1f4e214fea8" x="521" y="290" width="100" height="20" origin="4" srcId="14"/>
			<textContent><![CDATA[541609.0]]></textContent>
		</text>
		<text textHeight="12.578125" lineSpacingFactor="1.2578125" leadingOffset="-2.524414">
			<reportElement uuid="f113d5ad-3f73-400a-938d-ae09cc30d3c5" x="21" y="415" width="100" height="20" origin="4" srcId="10"/>
			<textContent><![CDATA[Childerich Fries]]></textContent>
		</text>
		<text textHeight="12.578125" lineSpacingFactor="1.2578125" leadingOffset="-2.524414" valueClass="java.lang.Integer">
			<reportElement uuid="a1803140-cd56-49d0-915e-b4cdeee35f68" x="252" y="415" width="100" height="20" origin="4" srcId="11"/>
			<textContent><![CDATA[558]]></textContent>
		</text>
		<text textHeight="12.578125" lineSpacingFactor="1.2578125" leadingOffset="-2.524414" valueClass="java.lang.Integer">
			<reportElement uuid="9f9fefa2-eee1-4f3e-9956-c66d37e34e00" x="137" y="415" width="100" height="20" origin="4" srcId="12"/>
			<textContent><![CDATA[19]]></textContent>
		</text>
		<text textHeight="12.578125" lineSpacingFactor="1.2578125" leadingOffset="-2.524414" valueClass="java.lang.Integer">
			<reportElement uuid="e96a05ce-cdb9-4ee9-8e21-a371d7a53279" x="375" y="415" width="100" height="20" origin="4" srcId="13"/>
			<textContent><![CDATA[7]]></textContent>
		</text>
		<text textHeight="12.578125" lineSpacingFactor="1.2578125" leadingOffset="-2.524414" valueClass="java.lang.Float">
			<reportElement uuid="09dae523-39b7-4d38-93f8-c1f4e214fea8" x="521" y="415" width="100" height="20" origin="4" srcId="14"/>
			<textContent><![CDATA[7436530.0]]></textContent>
		</text>
		<text textHeight="12.578125" lineSpacingFactor="1.2578125" leadingOffset="-2.524414">
			<reportElement uuid="f113d5ad-3f73-400a-938d-ae09cc30d3c5" x="21" y="540" width="100" height="20" origin="4" srcId="10"/>
			<textContent><![CDATA[Frederika Heldman]]></textContent>
		</text>
		<text textHeight="12.578125" lineSpacingFactor="1.2578125" leadingOffset="-2.524414" valueClass="java.lang.Integer">
			<reportElement uuid="a1803140-cd56-49d0-915e-b4cdeee35f68" x="252" y="540" width="100" height="20" origin="4" srcId="11"/>
			<textContent><![CDATA[48]]></textContent>
		</text>
		<text textHeight="12.578125" lineSpacingFactor="1.2578125" leadingOffset="-2.524414" valueClass="java.lang.Integer">
			<reportElement uuid="9f9fefa2-eee1-4f3e-9956-c66d37e34e00" x="137" y="540" width="100" height="20" origin="4" srcId="12"/>
			<textContent><![CDATA[19]]></textContent>
		</text>
		<text textHeight="12.578125" lineSpacingFactor="1.2578125" leadingOffset="-2.524414" valueClass="java.lang.Integer">
			<reportElement uuid="e96a05ce-cdb9-4ee9-8e21-a371d7a53279" x="375" y="540" width="100" height="20" origin="4" srcId="13"/>
			<textContent><![CDATA[34]]></textContent>
		</text>
		<text textHeight="12.578125" lineSpacingFactor="1.2578125" leadingOffset="-2.524414" valueClass="java.lang.Float">
			<reportElement uuid="09dae523-39b7-4d38-93f8-c1f4e214fea8" x="521" y="540" width="100" height="20" origin="4" srcId="14"/>
			<textContent><![CDATA[8080230.0]]></textContent>
		</text>
	</page>
	<page>
		<line>
			<reportElement uuid="27275c97-40e2-4939-8900-7574da372a65" x="20" y="93" width="555" height="1" origin="3" srcId="4"/>
		</line>
		<text textHeight="12.578125" lineSpacingFactor="1.2578125" leadingOffset="-2.524414">
			<reportElement uuid="e83b38b2-0c41-4e74-ad13-0a4c8a94c51b" x="21" y="74" width="100" height="20" origin="3" srcId="5"/>
			<font isBold="true"/>
			<textContent><![CDATA[Proveedor]]></textContent>
		</text>
		<text textHeight="12.578125" lineSpacingFactor="1.2578125" leadingOffset="-2.524414">
			<reportElement uuid="530ce9ef-a10f-4700-b00a-4ead60aebb85" x="252" y="73" width="100" height="20" origin="3" srcId="6"/>
			<font isBold="true"/>
			<textContent><![CDATA[Código postal]]></textContent>
		</text>
		<text textHeight="12.578125" lineSpacingFactor="1.2578125" leadingOffset="-2.524414">
			<reportElement uuid="132e4a73-1ca8-4139-9e8c-c0142ad86571" x="137" y="73" width="100" height="20" origin="3" srcId="7"/>
			<font isBold="true"/>
			<textContent><![CDATA[Empleado]]></textContent>
		</text>
		<text textHeight="12.578125" lineSpacingFactor="1.2578125" leadingOffset="-2.524414">
			<reportElement uuid="1ce41270-2a0f-4f83-adbe-fd7fbfc19e7e" x="375" y="73" width="100" height="20" origin="3" srcId="8"/>
			<font isBold="true"/>
			<textContent><![CDATA[Producto]]></textContent>
		</text>
		<text textHeight="12.578125" lineSpacingFactor="1.2578125" leadingOffset="-2.524414">
			<reportElement uuid="bdc6ba74-6f4c-4ecf-98ba-ab21b873471a" x="521" y="73" width="100" height="20" origin="3" srcId="9"/>
			<font isBold="true"/>
			<textContent><![CDATA[TOTAL]]></textContent>
		</text>
		<text textHeight="12.578125" lineSpacingFactor="1.2578125" leadingOffset="-2.524414">
			<reportElement uuid="f113d5ad-3f73-400a-938d-ae09cc30d3c5" x="21" y="165" width="100" height="20" origin="4" srcId="10"/>
			<textContent><![CDATA[Brita icolai]]></textContent>
		</text>
		<text textHeight="12.578125" lineSpacingFactor="1.2578125" leadingOffset="-2.524414" valueClass="java.lang.Integer">
			<reportElement uuid="a1803140-cd56-49d0-915e-b4cdeee35f68" x="252" y="165" width="100" height="20" origin="4" srcId="11"/>
			<textContent><![CDATA[208]]></textContent>
		</text>
		<text textHeight="12.578125" lineSpacingFactor="1.2578125" leadingOffset="-2.524414" valueClass="java.lang.Integer">
			<reportElement uuid="9f9fefa2-eee1-4f3e-9956-c66d37e34e00" x="137" y="165" width="100" height="20" origin="4" srcId="12"/>
			<textContent><![CDATA[4]]></textContent>
		</text>
		<text textHeight="12.578125" lineSpacingFactor="1.2578125" leadingOffset="-2.524414" valueClass="java.lang.Integer">
			<reportElement uuid="e96a05ce-cdb9-4ee9-8e21-a371d7a53279" x="375" y="165" width="100" height="20" origin="4" srcId="13"/>
			<textContent><![CDATA[44]]></textContent>
		</text>
		<text textHeight="12.578125" lineSpacingFactor="1.2578125" leadingOffset="-2.524414" valueClass="java.lang.Float">
			<reportElement uuid="09dae523-39b7-4d38-93f8-c1f4e214fea8" x="521" y="165" width="100" height="20" origin="4" srcId="14"/>
			<textContent><![CDATA[5247380.0]]></textContent>
		</text>
		<text textHeight="12.578125" lineSpacingFactor="1.2578125" leadingOffset="-2.524414">
			<reportElement uuid="f113d5ad-3f73-400a-938d-ae09cc30d3c5" x="21" y="290" width="100" height="20" origin="4" srcId="10"/>
			<textContent><![CDATA[Berend Wassermann]]></textContent>
		</text>
		<text textHeight="12.578125" lineSpacingFactor="1.2578125" leadingOffset="-2.524414" valueClass="java.lang.Integer">
			<reportElement uuid="a1803140-cd56-49d0-915e-b4cdeee35f68" x="252" y="290" width="100" height="20" origin="4" srcId="11"/>
			<textContent><![CDATA[887]]></textContent>
		</text>
		<text textHeight="12.578125" lineSpacingFactor="1.2578125" leadingOffset="-2.524414" valueClass="java.lang.Integer">
			<reportElement uuid="9f9fefa2-eee1-4f3e-9956-c66d37e34e00" x="137" y="290" width="100" height="20" origin="4" srcId="12"/>
			<textContent><![CDATA[20]]></textContent>
		</text>
		<text textHeight="12.578125" lineSpacingFactor="1.2578125" leadingOffset="-2.524414" valueClass="java.lang.Integer">
			<reportElement uuid="e96a05ce-cdb9-4ee9-8e21-a371d7a53279" x="375" y="290" width="100" height="20" origin="4" srcId="13"/>
			<textContent><![CDATA[40]]></textContent>
		</text>
		<text textHeight="12.578125" lineSpacingFactor="1.2578125" leadingOffset="-2.524414" valueClass="java.lang.Float">
			<reportElement uuid="09dae523-39b7-4d38-93f8-c1f4e214fea8" x="521" y="290" width="100" height="20" origin="4" srcId="14"/>
			<textContent><![CDATA[7263480.0]]></textContent>
		</text>
		<text textHeight="12.578125" lineSpacingFactor="1.2578125" leadingOffset="-2.524414">
			<reportElement uuid="f113d5ad-3f73-400a-938d-ae09cc30d3c5" x="21" y="415" width="100" height="20" origin="4" srcId="10"/>
			<textContent><![CDATA[Amica Forster]]></textContent>
		</text>
		<text textHeight="12.578125" lineSpacingFactor="1.2578125" leadingOffset="-2.524414" valueClass="java.lang.Integer">
			<reportElement uuid="a1803140-cd56-49d0-915e-b4cdeee35f68" x="252" y="415" width="100" height="20" origin="4" srcId="11"/>
			<textContent><![CDATA[233]]></textContent>
		</text>
		<text textHeight="12.578125" lineSpacingFactor="1.2578125" leadingOffset="-2.524414" valueClass="java.lang.Integer">
			<reportElement uuid="9f9fefa2-eee1-4f3e-9956-c66d37e34e00" x="137" y="415" width="100" height="20" origin="4" srcId="12"/>
			<textContent><![CDATA[43]]></textContent>
		</text>
		<text textHeight="12.578125" lineSpacingFactor="1.2578125" leadingOffset="-2.524414" valueClass="java.lang.Integer">
			<reportElement uuid="e96a05ce-cdb9-4ee9-8e21-a371d7a53279" x="375" y="415" width="100" height="20" origin="4" srcId="13"/>
			<textContent><![CDATA[6]]></textContent>
		</text>
		<text textHeight="12.578125" lineSpacingFactor="1.2578125" leadingOffset="-2.524414" valueClass="java.lang.Float">
			<reportElement uuid="09dae523-39b7-4d38-93f8-c1f4e214fea8" x="521" y="415" width="100" height="20" origin="4" srcId="14"/>
			<textContent><![CDATA[3914930.0]]></textContent>
		</text>
		<text textHeight="12.578125" lineSpacingFactor="1.2578125" leadingOffset="-2.524414">
			<reportElement uuid="f113d5ad-3f73-400a-938d-ae09cc30d3c5" x="21" y="540" width="100" height="20" origin="4" srcId="10"/>
			<textContent><![CDATA[Almut Horkheimer]]></textContent>
		</text>
		<text textHeight="12.578125" lineSpacingFactor="1.2578125" leadingOffset="-2.524414" valueClass="java.lang.Integer">
			<reportElement uuid="a1803140-cd56-49d0-915e-b4cdeee35f68" x="252" y="540" width="100" height="20" origin="4" srcId="11"/>
			<textContent><![CDATA[372]]></textContent>
		</text>
		<text textHeight="12.578125" lineSpacingFactor="1.2578125" leadingOffset="-2.524414" valueClass="java.lang.Integer">
			<reportElement uuid="9f9fefa2-eee1-4f3e-9956-c66d37e34e00" x="137" y="540" width="100" height="20" origin="4" srcId="12"/>
			<textContent><![CDATA[1]]></textContent>
		</text>
		<text textHeight="12.578125" lineSpacingFactor="1.2578125" leadingOffset="-2.524414" valueClass="java.lang.Integer">
			<reportElement uuid="e96a05ce-cdb9-4ee9-8e21-a371d7a53279" x="375" y="540" width="100" height="20" origin="4" srcId="13"/>
			<textContent><![CDATA[34]]></textContent>
		</text>
		<text textHeight="12.578125" lineSpacingFactor="1.2578125" leadingOffset="-2.524414" valueClass="java.lang.Float">
			<reportElement uuid="09dae523-39b7-4d38-93f8-c1f4e214fea8" x="521" y="540" width="100" height="20" origin="4" srcId="14"/>
			<textContent><![CDATA[5973000.0]]></textContent>
		</text>
	</page>
	<page>
		<line>
			<reportElement uuid="27275c97-40e2-4939-8900-7574da372a65" x="20" y="93" width="555" height="1" origin="3" srcId="4"/>
		</line>
		<text textHeight="12.578125" lineSpacingFactor="1.2578125" leadingOffset="-2.524414">
			<reportElement uuid="e83b38b2-0c41-4e74-ad13-0a4c8a94c51b" x="21" y="74" width="100" height="20" origin="3" srcId="5"/>
			<font isBold="true"/>
			<textContent><![CDATA[Proveedor]]></textContent>
		</text>
		<text textHeight="12.578125" lineSpacingFactor="1.2578125" leadingOffset="-2.524414">
			<reportElement uuid="530ce9ef-a10f-4700-b00a-4ead60aebb85" x="252" y="73" width="100" height="20" origin="3" srcId="6"/>
			<font isBold="true"/>
			<textContent><![CDATA[Código postal]]></textContent>
		</text>
		<text textHeight="12.578125" lineSpacingFactor="1.2578125" leadingOffset="-2.524414">
			<reportElement uuid="132e4a73-1ca8-4139-9e8c-c0142ad86571" x="137" y="73" width="100" height="20" origin="3" srcId="7"/>
			<font isBold="true"/>
			<textContent><![CDATA[Empleado]]></textContent>
		</text>
		<text textHeight="12.578125" lineSpacingFactor="1.2578125" leadingOffset="-2.524414">
			<reportElement uuid="1ce41270-2a0f-4f83-adbe-fd7fbfc19e7e" x="375" y="73" width="100" height="20" origin="3" srcId="8"/>
			<font isBold="true"/>
			<textContent><![CDATA[Producto]]></textContent>
		</text>
		<text textHeight="12.578125" lineSpacingFactor="1.2578125" leadingOffset="-2.524414">
			<reportElement uuid="bdc6ba74-6f4c-4ecf-98ba-ab21b873471a" x="521" y="73" width="100" height="20" origin="3" srcId="9"/>
			<font isBold="true"/>
			<textContent><![CDATA[TOTAL]]></textContent>
		</text>
		<text textHeight="12.578125" lineSpacingFactor="1.2578125" leadingOffset="-2.524414">
			<reportElement uuid="f113d5ad-3f73-400a-938d-ae09cc30d3c5" x="21" y="165" width="100" height="20" origin="4" srcId="10"/>
			<textContent><![CDATA[Thusnelda Imhof]]></textContent>
		</text>
		<text textHeight="12.578125" lineSpacingFactor="1.2578125" leadingOffset="-2.524414" valueClass="java.lang.Integer">
			<reportElement uuid="a1803140-cd56-49d0-915e-b4cdeee35f68" x="252" y="165" width="100" height="20" origin="4" srcId="11"/>
			<textContent><![CDATA[704]]></textContent>
		</text>
		<text textHeight="12.578125" lineSpacingFactor="1.2578125" leadingOffset="-2.524414" valueClass="java.lang.Integer">
			<reportElement uuid="9f9fefa2-eee1-4f3e-9956-c66d37e34e00" x="137" y="165" width="100" height="20" origin="4" srcId="12"/>
			<textContent><![CDATA[20]]></textContent>
		</text>
		<text textHeight="12.578125" lineSpacingFactor="1.2578125" leadingOffset="-2.524414" valueClass="java.lang.Integer">
			<reportElement uuid="e96a05ce-cdb9-4ee9-8e21-a371d7a53279" x="375" y="165" width="100" height="20" origin="4" srcId="13"/>
			<textContent><![CDATA[25]]></textContent>
		</text>
		<text textHeight="12.578125" lineSpacingFactor="1.2578125" leadingOffset="-2.524414" valueClass="java.lang.Float">
			<reportElement uuid="09dae523-39b7-4d38-93f8-c1f4e214fea8" x="521" y="165" width="100" height="20" origin="4" srcId="14"/>
			<textContent><![CDATA[8520570.0]]></textContent>
		</text>
		<text textHeight="12.578125" lineSpacingFactor="1.2578125" leadingOffset="-2.524414">
			<reportElement uuid="f113d5ad-3f73-400a-938d-ae09cc30d3c5" x="21" y="290" width="100" height="20" origin="4" srcId="10"/>
			<textContent><![CDATA[Norea Timroth]]></textContent>
		</text>
		<text textHeight="12.578125" lineSpacingFactor="1.2578125" leadingOffset="-2.524414" valueClass="java.lang.Integer">
			<reportElement uuid="a1803140-cd56-49d0-915e-b4cdeee35f68" x="252" y="290" width="100" height="20" origin="4" srcId="11"/>
			<textContent><![CDATA[276]]></textContent>
		</text>
		<text textHeight="12.578125" lineSpacingFactor="1.2578125" leadingOffset="-2.524414" valueClass="java.lang.Integer">
			<reportElement uuid="9f9fefa2-eee1-4f3e-9956-c66d37e34e00" x="137" y="290" width="100" height="20" origin="4" srcId="12"/>
			<textContent><![CDATA[17]]></textContent>
		</text>
		<text textHeight="12.578125" lineSpacingFactor="1.2578125" leadingOffset="-2.524414" valueClass="java.lang.Integer">
			<reportElement uuid="e96a05ce-cdb9-4ee9-8e21-a371d7a53279" x="375" y="290" width="100" height="20" origin="4" srcId="13"/>
			<textContent><![CDATA[14]]></textContent>
		</text>
		<text textHeight="12.578125" lineSpacingFactor="1.2578125" leadingOffset="-2.524414" valueClass="java.lang.Float">
			<reportElement uuid="09dae523-39b7-4d38-93f8-c1f4e214fea8" x="521" y="290" width="100" height="20" origin="4" srcId="14"/>
			<textContent><![CDATA[2118380.0]]></textContent>
		</text>
		<text textHeight="12.578125" lineSpacingFactor="1.2578125" leadingOffset="-2.524414">
			<reportElement uuid="f113d5ad-3f73-400a-938d-ae09cc30d3c5" x="21" y="415" width="100" height="20" origin="4" srcId="10"/>
			<textContent><![CDATA[Cesar Jost]]></textContent>
		</text>
		<text textHeight="12.578125" lineSpacingFactor="1.2578125" leadingOffset="-2.524414" valueClass="java.lang.Integer">
			<reportElement uuid="a1803140-cd56-49d0-915e-b4cdeee35f68" x="252" y="415" width="100" height="20" origin="4" srcId="11"/>
			<textContent><![CDATA[372]]></textContent>
		</text>
		<text textHeight="12.578125" lineSpacingFactor="1.2578125" leadingOffset="-2.524414" valueClass="java.lang.Integer">
			<reportElement uuid="9f9fefa2-eee1-4f3e-9956-c66d37e34e00" x="137" y="415" width="100" height="20" origin="4" srcId="12"/>
			<textContent><![CDATA[12]]></textContent>
		</text>
		<text textHeight="12.578125" lineSpacingFactor="1.2578125" leadingOffset="-2.524414" valueClass="java.lang.Integer">
			<reportElement uuid="e96a05ce-cdb9-4ee9-8e21-a371d7a53279" x="375" y="415" width="100" height="20" origin="4" srcId="13"/>
			<textContent><![CDATA[9]]></textContent>
		</text>
		<text textHeight="12.578125" lineSpacingFactor="1.2578125" leadingOffset="-2.524414" valueClass="java.lang.Float">
			<reportElement uuid="09dae523-39b7-4d38-93f8-c1f4e214fea8" x="521" y="415" width="100" height="20" origin="4" srcId="14"/>
			<textContent><![CDATA[9219600.0]]></textContent>
		</text>
		<text textHeight="12.578125" lineSpacingFactor="1.2578125" leadingOffset="-2.524414">
			<reportElement uuid="f113d5ad-3f73-400a-938d-ae09cc30d3c5" x="21" y="540" width="100" height="20" origin="4" srcId="10"/>
			<textContent><![CDATA[Maita Keller]]></textContent>
		</text>
		<text textHeight="12.578125" lineSpacingFactor="1.2578125" leadingOffset="-2.524414" valueClass="java.lang.Integer">
			<reportElement uuid="a1803140-cd56-49d0-915e-b4cdeee35f68" x="252" y="540" width="100" height="20" origin="4" srcId="11"/>
			<textContent><![CDATA[704]]></textContent>
		</text>
		<text textHeight="12.578125" lineSpacingFactor="1.2578125" leadingOffset="-2.524414" valueClass="java.lang.Integer">
			<reportElement uuid="9f9fefa2-eee1-4f3e-9956-c66d37e34e00" x="137" y="540" width="100" height="20" origin="4" srcId="12"/>
			<textContent><![CDATA[15]]></textContent>
		</text>
		<text textHeight="12.578125" lineSpacingFactor="1.2578125" leadingOffset="-2.524414" valueClass="java.lang.Integer">
			<reportElement uuid="e96a05ce-cdb9-4ee9-8e21-a371d7a53279" x="375" y="540" width="100" height="20" origin="4" srcId="13"/>
			<textContent><![CDATA[50]]></textContent>
		</text>
		<text textHeight="12.578125" lineSpacingFactor="1.2578125" leadingOffset="-2.524414" valueClass="java.lang.Float">
			<reportElement uuid="09dae523-39b7-4d38-93f8-c1f4e214fea8" x="521" y="540" width="100" height="20" origin="4" srcId="14"/>
			<textContent><![CDATA[4416460.0]]></textContent>
		</text>
	</page>
	<page>
		<line>
			<reportElement uuid="27275c97-40e2-4939-8900-7574da372a65" x="20" y="93" width="555" height="1" origin="3" srcId="4"/>
		</line>
		<text textHeight="12.578125" lineSpacingFactor="1.2578125" leadingOffset="-2.524414">
			<reportElement uuid="e83b38b2-0c41-4e74-ad13-0a4c8a94c51b" x="21" y="74" width="100" height="20" origin="3" srcId="5"/>
			<font isBold="true"/>
			<textContent><![CDATA[Proveedor]]></textContent>
		</text>
		<text textHeight="12.578125" lineSpacingFactor="1.2578125" leadingOffset="-2.524414">
			<reportElement uuid="530ce9ef-a10f-4700-b00a-4ead60aebb85" x="252" y="73" width="100" height="20" origin="3" srcId="6"/>
			<font isBold="true"/>
			<textContent><![CDATA[Código postal]]></textContent>
		</text>
		<text textHeight="12.578125" lineSpacingFactor="1.2578125" leadingOffset="-2.524414">
			<reportElement uuid="132e4a73-1ca8-4139-9e8c-c0142ad86571" x="137" y="73" width="100" height="20" origin="3" srcId="7"/>
			<font isBold="true"/>
			<textContent><![CDATA[Empleado]]></textContent>
		</text>
		<text textHeight="12.578125" lineSpacingFactor="1.2578125" leadingOffset="-2.524414">
			<reportElement uuid="1ce41270-2a0f-4f83-adbe-fd7fbfc19e7e" x="375" y="73" width="100" height="20" origin="3" srcId="8"/>
			<font isBold="true"/>
			<textContent><![CDATA[Producto]]></textContent>
		</text>
		<text textHeight="12.578125" lineSpacingFactor="1.2578125" leadingOffset="-2.524414">
			<reportElement uuid="bdc6ba74-6f4c-4ecf-98ba-ab21b873471a" x="521" y="73" width="100" height="20" origin="3" srcId="9"/>
			<font isBold="true"/>
			<textContent><![CDATA[TOTAL]]></textContent>
		</text>
		<text textHeight="12.578125" lineSpacingFactor="1.2578125" leadingOffset="-2.524414">
			<reportElement uuid="f113d5ad-3f73-400a-938d-ae09cc30d3c5" x="21" y="165" width="100" height="20" origin="4" srcId="10"/>
			<textContent><![CDATA[Chlothar J├ñger]]></textContent>
		</text>
		<text textHeight="12.578125" lineSpacingFactor="1.2578125" leadingOffset="-2.524414" valueClass="java.lang.Integer">
			<reportElement uuid="a1803140-cd56-49d0-915e-b4cdeee35f68" x="252" y="165" width="100" height="20" origin="4" srcId="11"/>
			<textContent><![CDATA[100]]></textContent>
		</text>
		<text textHeight="12.578125" lineSpacingFactor="1.2578125" leadingOffset="-2.524414" valueClass="java.lang.Integer">
			<reportElement uuid="9f9fefa2-eee1-4f3e-9956-c66d37e34e00" x="137" y="165" width="100" height="20" origin="4" srcId="12"/>
			<textContent><![CDATA[4]]></textContent>
		</text>
		<text textHeight="12.578125" lineSpacingFactor="1.2578125" leadingOffset="-2.524414" valueClass="java.lang.Integer">
			<reportElement uuid="e96a05ce-cdb9-4ee9-8e21-a371d7a53279" x="375" y="165" width="100" height="20" origin="4" srcId="13"/>
			<textContent><![CDATA[3]]></textContent>
		</text>
		<text textHeight="12.578125" lineSpacingFactor="1.2578125" leadingOffset="-2.524414" valueClass="java.lang.Float">
			<reportElement uuid="09dae523-39b7-4d38-93f8-c1f4e214fea8" x="521" y="165" width="100" height="20" origin="4" srcId="14"/>
			<textContent><![CDATA[4820790.0]]></textContent>
		</text>
		<text textHeight="12.578125" lineSpacingFactor="1.2578125" leadingOffset="-2.524414">
			<reportElement uuid="f113d5ad-3f73-400a-938d-ae09cc30d3c5" x="21" y="290" width="100" height="20" origin="4" srcId="10"/>
			<textContent><![CDATA[Balte  Wegener]]></textContent>
		</text>
		<text textHeight="12.578125" lineSpacingFactor="1.2578125" leadingOffset="-2.524414" valueClass="java.lang.Integer">
			<reportElement uuid="a1803140-cd56-49d0-915e-b4cdeee35f68" x="252" y="290" width="100" height="20" origin="4" srcId="11"/>
			<textContent><![CDATA[404]]></textContent>
		</text>
		<text textHeight="12.578125" lineSpacingFactor="1.2578125" leadingOffset="-2.524414" valueClass="java.lang.Integer">
			<reportElement uuid="9f9fefa2-eee1-4f3e-9956-c66d37e34e00" x="137" y="290" width="100" height="20" origin="4" srcId="12"/>
			<textContent><![CDATA[47]]></textContent>
		</text>
		<text textHeight="12.578125" lineSpacingFactor="1.2578125" leadingOffset="-2.524414" valueClass="java.lang.Integer">
			<reportElement uuid="e96a05ce-cdb9-4ee9-8e21-a371d7a53279" x="375" y="290" width="100" height="20" origin="4" srcId="13"/>
			<textContent><![CDATA[35]]></textContent>
		</text>
		<text textHeight="12.578125" lineSpacingFactor="1.2578125" leadingOffset="-2.524414" valueClass="java.lang.Float">
			<reportElement uuid="09dae523-39b7-4d38-93f8-c1f4e214fea8" x="521" y="290" width="100" height="20" origin="4" srcId="14"/>
			<textContent><![CDATA[3887460.0]]></textContent>
		</text>
		<text textHeight="12.578125" lineSpacingFactor="1.2578125" leadingOffset="-2.524414">
			<reportElement uuid="f113d5ad-3f73-400a-938d-ae09cc30d3c5" x="21" y="415" width="100" height="20" origin="4" srcId="10"/>
			<textContent><![CDATA[Ailine  Altmann]]></textContent>
		</text>
		<text textHeight="12.578125" lineSpacingFactor="1.2578125" leadingOffset="-2.524414" valueClass="java.lang.Integer">
			<reportElement uuid="a1803140-cd56-49d0-915e-b4cdeee35f68" x="252" y="415" width="100" height="20" origin="4" srcId="11"/>
			<textContent><![CDATA[748]]></textContent>
		</text>
		<text textHeight="12.578125" lineSpacingFactor="1.2578125" leadingOffset="-2.524414" valueClass="java.lang.Integer">
			<reportElement uuid="9f9fefa2-eee1-4f3e-9956-c66d37e34e00" x="137" y="415" width="100" height="20" origin="4" srcId="12"/>
			<textContent><![CDATA[8]]></textContent>
		</text>
		<text textHeight="12.578125" lineSpacingFactor="1.2578125" leadingOffset="-2.524414" valueClass="java.lang.Integer">
			<reportElement uuid="e96a05ce-cdb9-4ee9-8e21-a371d7a53279" x="375" y="415" width="100" height="20" origin="4" srcId="13"/>
			<textContent><![CDATA[47]]></textContent>
		</text>
		<text textHeight="12.578125" lineSpacingFactor="1.2578125" leadingOffset="-2.524414" valueClass="java.lang.Float">
			<reportElement uuid="09dae523-39b7-4d38-93f8-c1f4e214fea8" x="521" y="415" width="100" height="20" origin="4" srcId="14"/>
			<textContent><![CDATA[2001080.0]]></textContent>
		</text>
		<text textHeight="12.578125" lineSpacingFactor="1.2578125" leadingOffset="-2.524414">
			<reportElement uuid="f113d5ad-3f73-400a-938d-ae09cc30d3c5" x="21" y="540" width="100" height="20" origin="4" srcId="10"/>
			<textContent><![CDATA[Notburga Albrecht]]></textContent>
		</text>
		<text textHeight="12.578125" lineSpacingFactor="1.2578125" leadingOffset="-2.524414" valueClass="java.lang.Integer">
			<reportElement uuid="a1803140-cd56-49d0-915e-b4cdeee35f68" x="252" y="540" width="100" height="20" origin="4" srcId="11"/>
			<textContent><![CDATA[716]]></textContent>
		</text>
		<text textHeight="12.578125" lineSpacingFactor="1.2578125" leadingOffset="-2.524414" valueClass="java.lang.Integer">
			<reportElement uuid="9f9fefa2-eee1-4f3e-9956-c66d37e34e00" x="137" y="540" width="100" height="20" origin="4" srcId="12"/>
			<textContent><![CDATA[48]]></textContent>
		</text>
		<text textHeight="12.578125" lineSpacingFactor="1.2578125" leadingOffset="-2.524414" valueClass="java.lang.Integer">
			<reportElement uuid="e96a05ce-cdb9-4ee9-8e21-a371d7a53279" x="375" y="540" width="100" height="20" origin="4" srcId="13"/>
			<textContent><![CDATA[47]]></textContent>
		</text>
		<text textHeight="12.578125" lineSpacingFactor="1.2578125" leadingOffset="-2.524414" valueClass="java.lang.Float">
			<reportElement uuid="09dae523-39b7-4d38-93f8-c1f4e214fea8" x="521" y="540" width="100" height="20" origin="4" srcId="14"/>
			<textContent><![CDATA[7027510.0]]></textContent>
		</text>
	</page>
	<page>
		<line>
			<reportElement uuid="27275c97-40e2-4939-8900-7574da372a65" x="20" y="93" width="555" height="1" origin="3" srcId="4"/>
		</line>
		<text textHeight="12.578125" lineSpacingFactor="1.2578125" leadingOffset="-2.524414">
			<reportElement uuid="e83b38b2-0c41-4e74-ad13-0a4c8a94c51b" x="21" y="74" width="100" height="20" origin="3" srcId="5"/>
			<font isBold="true"/>
			<textContent><![CDATA[Proveedor]]></textContent>
		</text>
		<text textHeight="12.578125" lineSpacingFactor="1.2578125" leadingOffset="-2.524414">
			<reportElement uuid="530ce9ef-a10f-4700-b00a-4ead60aebb85" x="252" y="73" width="100" height="20" origin="3" srcId="6"/>
			<font isBold="true"/>
			<textContent><![CDATA[Código postal]]></textContent>
		</text>
		<text textHeight="12.578125" lineSpacingFactor="1.2578125" leadingOffset="-2.524414">
			<reportElement uuid="132e4a73-1ca8-4139-9e8c-c0142ad86571" x="137" y="73" width="100" height="20" origin="3" srcId="7"/>
			<font isBold="true"/>
			<textContent><![CDATA[Empleado]]></textContent>
		</text>
		<text textHeight="12.578125" lineSpacingFactor="1.2578125" leadingOffset="-2.524414">
			<reportElement uuid="1ce41270-2a0f-4f83-adbe-fd7fbfc19e7e" x="375" y="73" width="100" height="20" origin="3" srcId="8"/>
			<font isBold="true"/>
			<textContent><![CDATA[Producto]]></textContent>
		</text>
		<text textHeight="12.578125" lineSpacingFactor="1.2578125" leadingOffset="-2.524414">
			<reportElement uuid="bdc6ba74-6f4c-4ecf-98ba-ab21b873471a" x="521" y="73" width="100" height="20" origin="3" srcId="9"/>
			<font isBold="true"/>
			<textContent><![CDATA[TOTAL]]></textContent>
		</text>
		<text textHeight="12.578125" lineSpacingFactor="1.2578125" leadingOffset="-2.524414">
			<reportElement uuid="f113d5ad-3f73-400a-938d-ae09cc30d3c5" x="21" y="165" width="100" height="20" origin="4" srcId="10"/>
			<textContent><![CDATA[Caruso Abicht]]></textContent>
		</text>
		<text textHeight="12.578125" lineSpacingFactor="1.2578125" leadingOffset="-2.524414" valueClass="java.lang.Integer">
			<reportElement uuid="a1803140-cd56-49d0-915e-b4cdeee35f68" x="252" y="165" width="100" height="20" origin="4" srcId="11"/>
			<textContent><![CDATA[56]]></textContent>
		</text>
		<text textHeight="12.578125" lineSpacingFactor="1.2578125" leadingOffset="-2.524414" valueClass="java.lang.Integer">
			<reportElement uuid="9f9fefa2-eee1-4f3e-9956-c66d37e34e00" x="137" y="165" width="100" height="20" origin="4" srcId="12"/>
			<textContent><![CDATA[2]]></textContent>
		</text>
		<text textHeight="12.578125" lineSpacingFactor="1.2578125" leadingOffset="-2.524414" valueClass="java.lang.Integer">
			<reportElement uuid="e96a05ce-cdb9-4ee9-8e21-a371d7a53279" x="375" y="165" width="100" height="20" origin="4" srcId="13"/>
			<textContent><![CDATA[8]]></textContent>
		</text>
		<text textHeight="12.578125" lineSpacingFactor="1.2578125" leadingOffset="-2.524414" valueClass="java.lang.Float">
			<reportElement uuid="09dae523-39b7-4d38-93f8-c1f4e214fea8" x="521" y="165" width="100" height="20" origin="4" srcId="14"/>
			<textContent><![CDATA[2340250.0]]></textContent>
		</text>
		<text textHeight="12.578125" lineSpacingFactor="1.2578125" leadingOffset="-2.524414">
			<reportElement uuid="f113d5ad-3f73-400a-938d-ae09cc30d3c5" x="21" y="290" width="100" height="20" origin="4" srcId="10"/>
			<textContent><![CDATA[R├╝der Kloz]]></textContent>
		</text>
		<text textHeight="12.578125" lineSpacingFactor="1.2578125" leadingOffset="-2.524414" valueClass="java.lang.Integer">
			<reportElement uuid="a1803140-cd56-49d0-915e-b4cdeee35f68" x="252" y="290" width="100" height="20" origin="4" srcId="11"/>
			<textContent><![CDATA[724]]></textContent>
		</text>
		<text textHeight="12.578125" lineSpacingFactor="1.2578125" leadingOffset="-2.524414" valueClass="java.lang.Integer">
			<reportElement uuid="9f9fefa2-eee1-4f3e-9956-c66d37e34e00" x="137" y="290" width="100" height="20" origin="4" srcId="12"/>
			<textContent><![CDATA[17]]></textContent>
		</text>
		<text textHeight="12.578125" lineSpacingFactor="1.2578125" leadingOffset="-2.524414" valueClass="java.lang.Integer">
			<reportElement uuid="e96a05ce-cdb9-4ee9-8e21-a371d7a53279" x="375" y="290" width="100" height="20" origin="4" srcId="13"/>
			<textContent><![CDATA[25]]></textContent>
		</text>
		<text textHeight="12.578125" lineSpacingFactor="1.2578125" leadingOffset="-2.524414" valueClass="java.lang.Float">
			<reportElement uuid="09dae523-39b7-4d38-93f8-c1f4e214fea8" x="521" y="290" width="100" height="20" origin="4" srcId="14"/>
			<textContent><![CDATA[7056980.0]]></textContent>
		</text>
		<text textHeight="12.578125" lineSpacingFactor="1.2578125" leadingOffset="-2.524414" valueClass="java.lang.Integer">
			<reportElement uuid="0611e1ac-7cb7-4bd6-8dec-51e6be9e924e" x="475" y="388" width="100" height="20" origin="7" srcId="15"/>
			<textContent><![CDATA[13]]></textContent>
		</text>
	</page>
</jasperPrint>
